Workbook

Sheet Balance
A1: ESTADO DE SITUACION FINANCIERA | G1: 2021 | H1: 2022 | I1: 2023 | J1: 2024 | K1: 2025 | AE1: ANÁLISIS VERTICAL (% del Activo Total) | AK1: ANÁLISIS HORIZONTAL - Variación absoluta | AP1: ANÁLISIS HORIZONTAL - Variación %
G2: 46295 | H2: 46295 | I2: 46295 | J2: 46295 | K2: 46295 | AE2: 2021 | AF2: 2022 | AG2: 2023 | AH2: 2024 | AI2: 2025 | AK2: 2022/2021 | AL2: 2023/2022 | AM2: 2024/2023 | AN2: 2025/2024 | AP2: 2022/2021 | AQ2: 2023/2022 | AR2: 2024/2023 | AS2: 2025/2024
A3: Total del activo corriente | G3: =SUM(G4,G6,G7,G10,G11,G12,G14) -> 27607 | H3: =SUM(H4,H6,H7,H10,H11,H12,H14) -> 30205 | I3: =SUM(I4,I6,I7,I10,I11,I12,I14) -> 33532 | J3: =SUM(J4,J6,J7,J10,J11,J12,J14) -> 34033 | K3: =SUM(K4,K6,K7,K10,K11,K12,K14) -> 37766 | AE3: =IFERROR(G3/G$17,0) -> 0.33303175 | AF3: =IFERROR(H3/H$17,0) -> 0.35327072 | AG3: =IFERROR(I3/I$17,0) -> 0.37052343 | AH3: =IFERROR(J3/J$17,0) -> 0.36009565 | AI3: =IFERROR(K3/K$17,0) -> 0.37907395 | AK3: =IFERROR(H3-G3,0) -> 2598 | AL3: =IFERROR(I3-H3,0) -> 3327 | AM3: =IFERROR(J3-I3,0) -> 501 | AN3: =IFERROR(K3-J3,0) -> 3733 | AP3: =IFERROR((H3-G3)/G3,0) -> 0.094106567 | AQ3: =IFERROR((I3-H3)/H3,0) -> 0.11014733 | AR3: =IFERROR((J3-I3)/I3,0) -> 0.014940952 | AS3: =IFERROR((K3-J3)/J3,0) -> 0.10968766
A4: Efectivo y equivalentes | G4: 16487 | H4: 15689 | I4: 16286 | J4: 11975 | K4: 17164 | AE4: =IFERROR(G4/G$17,0) -> 0.19888776 | AF4: =IFERROR(H4/H$17,0) -> 0.18349493 | AG4: =IFERROR(I4/I$17,0) -> 0.17995779 | AH4: =IFERROR(J4/J$17,0) -> 0.12670483 | AI4: =IFERROR(K4/K$17,0) -> 0.17228261 | AK4: =IFERROR(H4-G4,0) -> -798 | AL4: =IFERROR(I4-H4,0) -> 597 | AM4: =IFERROR(J4-I4,0) -> -4311 | AN4: =IFERROR(K4-J4,0) -> 5189 | AP4: =IFERROR((H4-G4)/G4,0) -> -0.048401771 | AQ4: =IFERROR((I4-H4)/H4,0) -> 0.038052138 | AR4: =IFERROR((J4-I4)/I4,0) -> -0.26470588 | AS4: =IFERROR((K4-J4)/J4,0) -> 0.43331942
A5: Crecimiento de efectivo y equivalentes | G5: 0.0122 | H5: =IFERROR((H4-G4)/G4,0) -> -0.048401771 | I5: =IFERROR((I4-H4)/H4,0) -> 0.038052138 | J5: =IFERROR((J4-I4)/I4,0) -> -0.26470588 | K5: =IFERROR((K4-J4)/J4,0) -> 0.43331942 | AE5: =IFERROR(G5/G$17,0) -> 1.4717236e-07 | AF5: =IFERROR(H5/H$17,0) -> -5.6609596e-07 | AG5: =IFERROR(I5/I$17,0) -> 4.2047026e-07 | AH5: =IFERROR(J5/J$17,0) -> -2.8007944e-06 | AI5: =IFERROR(K5/K$17,0) -> 4.3494175e-06 | AK5: =IFERROR(H5-G5,0) -> -0.060601771 | AL5: =IFERROR(I5-H5,0) -> 0.08645391 | AM5: =IFERROR(J5-I5,0) -> -0.30275802 | AN5: =IFERROR(K5-J5,0) -> 0.6980253 | AP5: =IFERROR((H5-G5)/G5,0) -> -4.9673583 | AQ5: =IFERROR((I5-H5)/H5,0) -> -1.7861724 | AR5: =IFERROR((J5-I5)/I5,0) -> -7.9563996 | AS5: =IFERROR((K5-J5)/J5,0) -> -2.6369845
A6: Inversiones a corto plazo | G6: 2025 | H6: 2833 | I6: 3842 | J6: 3200 | K6: 1833 | AE6: =IFERROR(G6/G$17,0) -> 0.024428199 | AF6: =IFERROR(H6/H$17,0) -> 0.033134115 | AG6: =IFERROR(I6/I$17,0) -> 0.042453508 | AH6: =IFERROR(J6/J$17,0) -> 0.033858493 | AI6: =IFERROR(K6/K$17,0) -> 0.018398627 | AK6: =IFERROR(H6-G6,0) -> 808 | AL6: =IFERROR(I6-H6,0) -> 1009 | AM6: =IFERROR(J6-I6,0) -> -642 | AN6: =IFERROR(K6-J6,0) -> -1367 | AP6: =IFERROR((H6-G6)/G6,0) -> 0.39901235 | AQ6: =IFERROR((I6-H6)/H6,0) -> 0.35615955 | AR6: =IFERROR((J6-I6)/I6,0) -> -0.16710047 | AS6: =IFERROR((K6-J6)/J6,0) -> -0.4271875
A7: Créditos totales | G7: =SUM(G8,G9) -> 3809 | H7: =SUM(H8,H9) -> 4142 | I7: =SUM(I8,I9) -> 4680 | J7: =SUM(J8,J9) -> 7847 | K7: =SUM(K8,K9) -> 7549 | AE7: =IFERROR(G7/G$17,0) -> 0.045949141 | AF7: =IFERROR(H7/H$17,0) -> 0.048443878 | AG7: =IFERROR(I7/I$17,0) -> 0.051713279 | AH7: =IFERROR(J7/J$17,0) -> 0.083027372 | AI7: =IFERROR(K7/K$17,0) -> 0.075772632 | AK7: =IFERROR(H7-G7,0) -> 333 | AL7: =IFERROR(I7-H7,0) -> 538 | AM7: =IFERROR(J7-I7,0) -> 3167 | AN7: =IFERROR(K7-J7,0) -> -298 | AP7: =IFERROR((H7-G7)/G7,0) -> 0.087424521 | AQ7: =IFERROR((I7-H7)/H7,0) -> 0.12988894 | AR7: =IFERROR((J7-I7)/I7,0) -> 0.6767094 | AS7: =IFERROR((K7-J7)/J7,0) -> -0.037976297
A8: Total de cuentas por cobrar | G8: 3726 | H8: 3952 | I8: 4474 | J8: 7015 | K8: 7317 | AE8: =IFERROR(G8/G$17,0) -> 0.044947887 | AF8: =IFERROR(H8/H$17,0) -> 0.046221682 | AG8: =IFERROR(I8/I$17,0) -> 0.04943701 | AH8: =IFERROR(J8/J$17,0) -> 0.074224164 | AI8: =IFERROR(K8/K$17,0) -> 0.073443946 | AK8: =IFERROR(H8-G8,0) -> 226 | AL8: =IFERROR(I8-H8,0) -> 522 | AM8: =IFERROR(J8-I8,0) -> 2541 | AN8: =IFERROR(K8-J8,0) -> 302 | AP8: =IFERROR((H8-G8)/G8,0) -> 0.060654858 | AQ8: =IFERROR((I8-H8)/H8,0) -> 0.13208502 | AR8: =IFERROR((J8-I8)/I8,0) -> 0.56794814 | AS8: =IFERROR((K8-J8)/J8,0) -> 0.043050606
A9: Otros créditos | G9: 83 | H9: 190 | I9: 206 | J9: 832 | K9: 232 | AE9: =IFERROR(G9/G$17,0) -> 0.0010012546 | AF9: =IFERROR(H9/H$17,0) -> 0.0022221962 | AG9: =IFERROR(I9/I$17,0) -> 0.0022762682 | AH9: =IFERROR(J9/J$17,0) -> 0.0088032081 | AI9: =IFERROR(K9/K$17,0) -> 0.002328686 | AK9: =IFERROR(H9-G9,0) -> 107 | AL9: =IFERROR(I9-H9,0) -> 16 | AM9: =IFERROR(J9-I9,0) -> 626 | AN9: =IFERROR(K9-J9,0) -> -600 | AP9: =IFERROR((H9-G9)/G9,0) -> 1.2891566 | AQ9: =IFERROR((I9-H9)/H9,0) -> 0.084210526 | AR9: =IFERROR((J9-I9)/I9,0) -> 3.038835 | AS9: =IFERROR((K9-J9)/J9,0) -> -0.72115385
A10: Inventario | G10: - | H10: - | I10: - | J10: - | K10: - | AE10: =IFERROR(G10/G$17,0) -> 0 | AF10: =IFERROR(H10/H$17,0) -> 0 | AG10: =IFERROR(I10/I$17,0) -> 0 | AH10: =IFERROR(J10/J$17,0) -> 0 | AI10: =IFERROR(K10/K$17,0) -> 0 | AK10: =IFERROR(H10-G10,0) -> 0 | AL10: =IFERROR(I10-H10,0) -> 0 | AM10: =IFERROR(J10-I10,0) -> 0 | AN10: =IFERROR(K10-J10,0) -> 0 | AP10: =IFERROR((H10-G10)/G10,0) -> 0 | AQ10: =IFERROR((I10-H10)/H10,0) -> 0 | AR10: =IFERROR((J10-I10)/I10,0) -> 0 | AS10: =IFERROR((K10-J10)/J10,0) -> 0
A11: Gastos pagados por adelantado | G11: 613 | H11: 828 | I11: 1328 | J11: 1238 | K11: 985 | AE11: =IFERROR(G11/G$17,0) -> 0.007394808 | AF11: =IFERROR(H11/H$17,0) -> 0.0096840973 | AG11: =IFERROR(I11/I$17,0) -> 0.014674195 | AH11: =IFERROR(J11/J$17,0) -> 0.013099004 | AI11: =IFERROR(K11/K$17,0) -> 0.0098868781 | AK11: =IFERROR(H11-G11,0) -> 215 | AL11: =IFERROR(I11-H11,0) -> 500 | AM11: =IFERROR(J11-I11,0) -> -90 | AN11: =IFERROR(K11-J11,0) -> -253 | AP11: =IFERROR((H11-G11)/G11,0) -> 0.35073409 | AQ11: =IFERROR((I11-H11)/H11,0) -> 0.60386473 | AR11: =IFERROR((J11-I11)/I11,0) -> -0.067771084 | AS11: =IFERROR((K11-J11)/J11,0) -> -0.20436187
A12: División financiera, préstamos y arrendamientos corrientes | G12: - | H12: - | I12: - | J12: - | K12: - | AE12: =IFERROR(G12/G$17,0) -> 0 | AF12: =IFERROR(H12/H$17,0) -> 0 | AG12: =IFERROR(I12/I$17,0) -> 0 | AH12: =IFERROR(J12/J$17,0) -> 0 | AI12: =IFERROR(K12/K$17,0) -> 0 | AK12: =IFERROR(H12-G12,0) -> 0 | AL12: =IFERROR(I12-H12,0) -> 0 | AM12: =IFERROR(J12-I12,0) -> 0 | AN12: =IFERROR(K12-J12,0) -> 0 | AP12: =IFERROR((H12-G12)/G12,0) -> 0 | AQ12: =IFERROR((I12-H12)/H12,0) -> 0 | AR12: =IFERROR((J12-I12)/I12,0) -> 0 | AS12: =IFERROR((K12-J12)/J12,0) -> 0
A13: División financiera, total de otros activos corrientes | G13: - | H13: - | I13: - | J13: - | K13: - | AE13: =IFERROR(G13/G$17,0) -> 0 | AF13: =IFERROR(H13/H$17,0) -> 0 | AG13: =IFERROR(I13/I$17,0) -> 0 | AH13: =IFERROR(J13/J$17,0) -> 0 | AI13: =IFERROR(K13/K$17,0) -> 0 | AK13: =IFERROR(H13-G13,0) -> 0 | AL13: =IFERROR(I13-H13,0) -> 0 | AM13: =IFERROR(J13-I13,0) -> 0 | AN13: =IFERROR(K13-J13,0) -> 0 | AP13: =IFERROR((H13-G13)/G13,0) -> 0 | AQ13: =IFERROR((I13-H13)/H13,0) -> 0 | AR13: =IFERROR((J13-I13)/I13,0) -> 0 | AS13: =IFERROR((K13-J13)/J13,0) -> 0
A14: Otros activos corrientes | G14: =SUM(G15,G16) -> 4673 | H14: =SUM(H15,H16) -> 6713 | I14: =SUM(I15,I16) -> 7396 | J14: =SUM(J15,J16) -> 9773 | K14: =SUM(K15,K16) -> 10235 | AE14: =IFERROR(G14/G$17,0) -> 0.056371839 | AF14: =IFERROR(H14/H$17,0) -> 0.078513702 | AG14: =IFERROR(I14/I$17,0) -> 0.08172466 | AH14: =IFERROR(J14/J$17,0) -> 0.10340595 | AI14: =IFERROR(K14/K$17,0) -> 0.10273319 | AK14: =IFERROR(H14-G14,0) -> 2040 | AL14: =IFERROR(I14-H14,0) -> 683 | AM14: =IFERROR(J14-I14,0) -> 2377 | AN14: =IFERROR(K14-J14,0) -> 462 | AP14: =IFERROR((H14-G14)/G14,0) -> 0.4365504 | AQ14: =IFERROR((I14-H14)/H14,0) -> 0.10174289 | AR14: =IFERROR((J14-I14)/I14,0) -> 0.32138994 | AS14: =IFERROR((K14-J14)/J14,0) -> 0.047273099
A15: Efectivo restringido | G15: 1052 | H15: 2346 | I15: 2699 | J15: 4264 | K15: 4198 | AE15: =IFERROR(G15/G$17,0) -> 0.0126906 | AF15: =IFERROR(H15/H$17,0) -> 0.027438276 | AG15: =IFERROR(I15/I$17,0) -> 0.029823534 | AH15: =IFERROR(J15/J$17,0) -> 0.045116441 | AI15: =IFERROR(K15/K$17,0) -> 0.042137172 | AK15: =IFERROR(H15-G15,0) -> 1294 | AL15: =IFERROR(I15-H15,0) -> 353 | AM15: =IFERROR(J15-I15,0) -> 1565 | AN15: =IFERROR(K15-J15,0) -> -66 | AP15: =IFERROR((H15-G15)/G15,0) -> 1.230038 | AQ15: =IFERROR((I15-H15)/H15,0) -> 0.15046888 | AR15: =IFERROR((J15-I15)/I15,0) -> 0.57984439 | AS15: =IFERROR((K15-J15)/J15,0) -> -0.015478424
A16: Total de otros activos corrientes | G16: 3621 | H16: 4367 | I16: 4697 | J16: 5509 | K16: 6037 | AE16: =IFERROR(G16/G$17,0) -> 0.043681239 | AF16: =IFERROR(H16/H$17,0) -> 0.051075426 | AG16: =IFERROR(I16/I$17,0) -> 0.051901126 | AH16: =IFERROR(J16/J$17,0) -> 0.058289511 | AI16: =IFERROR(K16/K$17,0) -> 0.060596023 | AK16: =IFERROR(H16-G16,0) -> 746 | AL16: =IFERROR(I16-H16,0) -> 330 | AM16: =IFERROR(J16-I16,0) -> 812 | AN16: =IFERROR(K16-J16,0) -> 528 | AP16: =IFERROR((H16-G16)/G16,0) -> 0.20602044 | AQ16: =IFERROR((I16-H16)/H16,0) -> 0.075566751 | AR16: =IFERROR((J16-I16)/I16,0) -> 0.1728763 | AS16: =IFERROR((K16-J16)/J16,0) -> 0.095843166
A17: Activos totales | G17: =SUM(G3,G19,G22,G23,G27) -> 82896 | H17: =SUM(H3,H19,H22,H23,H27) -> 85501 | I17: =SUM(I3,I19,I22,I23,I27) -> 90499 | J17: =SUM(J3,J19,J22,J23,J27) -> 94511 | K17: =SUM(K3,K19,K22,K23,K27) -> 99627 | AE17: =IFERROR(G17/G$17,0) -> 1 | AF17: =IFERROR(H17/H$17,0) -> 1 | AG17: =IFERROR(I17/I$17,0) -> 1 | AH17: =IFERROR(J17/J$17,0) -> 1 | AI17: =IFERROR(K17/K$17,0) -> 1 | AK17: =IFERROR(H17-G17,0) -> 2605 | AL17: =IFERROR(I17-H17,0) -> 4998 | AM17: =IFERROR(J17-I17,0) -> 4012 | AN17: =IFERROR(K17-J17,0) -> 5116 | AP17: =IFERROR((H17-G17)/G17,0) -> 0.031424918 | AQ17: =IFERROR((I17-H17)/H17,0) -> 0.058455457 | AR17: =IFERROR((J17-I17)/I17,0) -> 0.044331982 | AS17: =IFERROR((K17-J17)/J17,0) -> 0.054131265
A18: Crecimiento de activos totales | G18: 0.0244 | H18: =IFERROR((H17-G17)/G17,0) -> 0.031424918 | I18: =IFERROR((I17-H17)/H17,0) -> 0.058455457 | J18: =IFERROR((J17-I17)/I17,0) -> 0.044331982 | K18: =IFERROR((K17-J17)/J17,0) -> 0.054131265 | AE18: =IFERROR(G18/G$17,0) -> 2.9434472e-07 | AF18: =IFERROR(H18/H$17,0) -> 3.675386e-07 | AG18: =IFERROR(I18/I$17,0) -> 6.4592379e-07 | AH18: =IFERROR(J18/J$17,0) -> 4.690669e-07 | AI18: =IFERROR(K18/K$17,0) -> 5.4333931e-07 | AK18: =IFERROR(H18-G18,0) -> 0.007024918 | AL18: =IFERROR(I18-H18,0) -> 0.027030539 | AM18: =IFERROR(J18-I18,0) -> -0.014123475 | AN18: =IFERROR(K18-J18,0) -> 0.0097992836 | AP18: =IFERROR((H18-G18)/G18,0) -> 0.28790647 | AQ18: =IFERROR((I18-H18)/H18,0) -> 0.86016259 | AR18: =IFERROR((J18-I18)/I18,0) -> -0.24161089 | AS18: =IFERROR((K18-J18)/J18,0) -> 0.22104321
A19: Planta, propiedad y equipo, neto | G19: =SUM(G20,G21) -> 2110 | H19: =SUM(H20,H21) -> 2112 | I19: =SUM(I20,I21) -> 2116 | J19: =SUM(J20,J21) -> 2537 | K19: =SUM(K20,K21) -> 2591 | L19: =+H19-G19 -> 2 | M19: =+I19-H19 -> 4 | N19: =+J19-I19 -> 421 | O19: =+K19-J19 -> 54 | AE19: =IFERROR(G19/G$17,0) -> 0.02545358 | AF19: =IFERROR(H19/H$17,0) -> 0.024701465 | AG19: =IFERROR(I19/I$17,0) -> 0.023381474 | AH19: =IFERROR(J19/J$17,0) -> 0.026843436 | AI19: =IFERROR(K19/K$17,0) -> 0.026007006 | AK19: =IFERROR(H19-G19,0) -> 2 | AL19: =IFERROR(I19-H19,0) -> 4 | AM19: =IFERROR(J19-I19,0) -> 421 | AN19: =IFERROR(K19-J19,0) -> 54 | AP19: =IFERROR((H19-G19)/G19,0) -> 0.0009478673 | AQ19: =IFERROR((I19-H19)/H19,0) -> 0.0018939394 | AR19: =IFERROR((J19-I19)/I19,0) -> 0.1989603 | AS19: =IFERROR((K19-J19)/J19,0) -> 0.021284982
A20: Inmovilizado material bruto | G20: 3869 | H20: 4070 | I20: 4071 | J20: 4510 | K20: 4461 | L20: =+H20-G20 -> 201 | M20: =+I20-H20 -> 1 | N20: =+J20-I20 -> 439 | O20: =+K20-J20 -> -49 | AD20: =+H20-G20 -> 201 | AE20: =IFERROR(G20/G$17,0) -> 0.04667294 | AF20: =IFERROR(H20/H$17,0) -> 0.047601782 | AG20: =IFERROR(I20/I$17,0) -> 0.044983922 | AH20: =IFERROR(J20/J$17,0) -> 0.047719313 | AI20: =IFERROR(K20/K$17,0) -> 0.044777018 | AK20: =IFERROR(H20-G20,0) -> 201 | AL20: =IFERROR(I20-H20,0) -> 1 | AM20: =IFERROR(J20-I20,0) -> 439 | AN20: =IFERROR(K20-J20,0) -> -49 | AP20: =IFERROR((H20-G20)/G20,0) -> 0.051951409 | AQ20: =IFERROR((I20-H20)/H20,0) -> 0.00024570025 | AR20: =IFERROR((J20-I20)/I20,0) -> 0.10783591 | AS20: =IFERROR((K20-J20)/J20,0) -> -0.010864745
A21: Amortización acumulada | G21: -1759 | H21: -1958 | I21: -1955 | J21: -1973 | K21: -1870 | L21: =+H21-G21 -> -199 | M21: =+I21-H21 -> 3 | N21: =+J21-I21 -> -18 | O21: =+K21-J21 -> 103 | AE21: =IFERROR(G21/G$17,0) -> -0.021219359 | AF21: =IFERROR(H21/H$17,0) -> -0.022900317 | AG21: =IFERROR(I21/I$17,0) -> -0.021602449 | AH21: =IFERROR(J21/J$17,0) -> -0.020875877 | AI21: =IFERROR(K21/K$17,0) -> -0.018770012 | AK21: =IFERROR(H21-G21,0) -> -199 | AL21: =IFERROR(I21-H21,0) -> 3 | AM21: =IFERROR(J21-I21,0) -> -18 | AN21: =IFERROR(K21-J21,0) -> 103 | AP21: =IFERROR((H21-G21)/G21,0) -> 0.11313246 | AQ21: =IFERROR((I21-H21)/H21,0) -> -0.0015321757 | AR21: =IFERROR((J21-I21)/I21,0) -> 0.0092071611 | AS21: =IFERROR((K21-J21)/J21,0) -> -0.052204764
A22: Inversiones a largo plazo | G22: 1843 | H22: 2136 | I22: 1921 | J22: 2545 | K22: 999 | AE22: =IFERROR(G22/G$17,0) -> 0.022232677 | AF22: =IFERROR(H22/H$17,0) -> 0.024982164 | AG22: =IFERROR(I22/I$17,0) -> 0.021226754 | AH22: =IFERROR(J22/J$17,0) -> 0.026928082 | AI22: =IFERROR(K22/K$17,0) -> 0.010027402 | AK22: =IFERROR(H22-G22,0) -> 293 | AL22: =IFERROR(I22-H22,0) -> -215 | AM22: =IFERROR(J22-I22,0) -> 624 | AN22: =IFERROR(K22-J22,0) -> -1546 | AP22: =IFERROR((H22-G22)/G22,0) -> 0.15897992 | AQ22: =IFERROR((I22-H22)/H22,0) -> -0.10065543 | AR22: =IFERROR((J22-I22)/I22,0) -> 0.32483082 | AS22: =IFERROR((K22-J22)/J22,0) -> -0.60746562
A23: Activos intangibles | G23: =SUM(G24,G25) -> 44742 | H23: =SUM(H24,H25) -> 44443 | I23: =SUM(I24,I25) -> 45898 | J23: =SUM(J24,J25) -> 47990 | K23: =SUM(K24,K25) -> 50124 | AE23: =IFERROR(G23/G$17,0) -> 0.53973654 | AF23: =IFERROR(H23/H$17,0) -> 0.51979509 | AG23: =IFERROR(I23/I$17,0) -> 0.50716583 | AH23: =IFERROR(J23/J$17,0) -> 0.50777158 | AI23: =IFERROR(K23/K$17,0) -> 0.50311663 | AK23: =IFERROR(H23-G23,0) -> -299 | AL23: =IFERROR(I23-H23,0) -> 1455 | AM23: =IFERROR(J23-I23,0) -> 2092 | AN23: =IFERROR(K23-J23,0) -> 2134 | AP23: =IFERROR((H23-G23)/G23,0) -> -0.0066827589 | AQ23: =IFERROR((I23-H23)/H23,0) -> 0.032738564 | AR23: =IFERROR((J23-I23)/I23,0) -> 0.045579328 | AS23: =IFERROR((K23-J23)/J23,0) -> 0.044467597
A24: Fondo de comercio | G24: 15958 | H24: 17787 | I24: 17997 | J24: 18941 | K24: 19879 | AE24: =IFERROR(G24/G$17,0) -> 0.19250627 | AF24: =IFERROR(H24/H$17,0) -> 0.20803265 | AG24: =IFERROR(I24/I$17,0) -> 0.19886408 | AH24: =IFERROR(J24/J$17,0) -> 0.20041053 | AI24: =IFERROR(K24/K$17,0) -> 0.19953426 | AK24: =IFERROR(H24-G24,0) -> 1829 | AL24: =IFERROR(I24-H24,0) -> 210 | AM24: =IFERROR(J24-I24,0) -> 944 | AN24: =IFERROR(K24-J24,0) -> 938 | AP24: =IFERROR((H24-G24)/G24,0) -> 0.11461336 | AQ24: =IFERROR((I24-H24)/H24,0) -> 0.011806375 | AR24: =IFERROR((J24-I24)/I24,0) -> 0.052453187 | AS24: =IFERROR((K24-J24)/J24,0) -> 0.049522201
A25: Otros intangibles, total | G25: 28784 | H25: 26656 | I25: 27901 | J25: 29049 | K25: 30245 | AE25: =IFERROR(G25/G$17,0) -> 0.34723026 | AF25: =IFERROR(H25/H$17,0) -> 0.31176244 | AG25: =IFERROR(I25/I$17,0) -> 0.30830175 | AH25: =IFERROR(J25/J$17,0) -> 0.30736105 | AI25: =IFERROR(K25/K$17,0) -> 0.30358236 | AK25: =IFERROR(H25-G25,0) -> -2128 | AL25: =IFERROR(I25-H25,0) -> 1245 | AM25: =IFERROR(J25-I25,0) -> 1148 | AN25: =IFERROR(K25-J25,0) -> 1196 | AP25: =IFERROR((H25-G25)/G25,0) -> -0.073929961 | AQ25: =IFERROR((I25-H25)/H25,0) -> 0.046706182 | AR25: =IFERROR((J25-I25)/I25,0) -> 0.041145479 | AS25: =IFERROR((K25-J25)/J25,0) -> 0.041171813
A26: División financiera, préstamos y arrendamientos a largo plazo | G26: - | H26: - | I26: - | J26: - | K26: - | AE26: =IFERROR(G26/G$17,0) -> 0 | AF26: =IFERROR(H26/H$17,0) -> 0 | AG26: =IFERROR(I26/I$17,0) -> 0 | AH26: =IFERROR(J26/J$17,0) -> 0 | AI26: =IFERROR(K26/K$17,0) -> 0 | AK26: =IFERROR(H26-G26,0) -> 0 | AL26: =IFERROR(I26-H26,0) -> 0 | AM26: =IFERROR(J26-I26,0) -> 0 | AN26: =IFERROR(K26-J26,0) -> 0 | AP26: =IFERROR((H26-G26)/G26,0) -> 0 | AQ26: =IFERROR((I26-H26)/H26,0) -> 0 | AR26: =IFERROR((J26-I26)/I26,0) -> 0 | AS26: =IFERROR((K26-J26)/J26,0) -> 0
A27: Total de otros activos | G27: =SUM(G28:G32) -> 6594 | H27: =SUM(H28:H32) -> 6605 | I27: =SUM(I28:I32) -> 7032 | J27: =SUM(J28:J32) -> 7406 | K27: =SUM(K28:K32) -> 8147 | AE27: =IFERROR(G27/G$17,0) -> 0.079545455 | AF27: =IFERROR(H27/H$17,0) -> 0.077250558 | AG27: =IFERROR(I27/I$17,0) -> 0.077702516 | AH27: =IFERROR(J27/J$17,0) -> 0.078361249 | AI27: =IFERROR(K27/K$17,0) -> 0.081775021 | AK27: =IFERROR(H27-G27,0) -> 11 | AL27: =IFERROR(I27-H27,0) -> 427 | AM27: =IFERROR(J27-I27,0) -> 374 | AN27: =IFERROR(K27-J27,0) -> 741 | AP27: =IFERROR((H27-G27)/G27,0) -> 0.0016681832 | AQ27: =IFERROR((I27-H27)/H27,0) -> 0.064647994 | AR27: =IFERROR((J27-I27)/I27,0) -> 0.053185438 | AS27: =IFERROR((K27-J27)/J27,0) -> 0.10005401
A28: Préstamos por cobrar a largo plazo | G28: - | H28: - | I28: - | J28: - | K28: - | AE28: =IFERROR(G28/G$17,0) -> 0 | AF28: =IFERROR(H28/H$17,0) -> 0 | AG28: =IFERROR(I28/I$17,0) -> 0 | AH28: =IFERROR(J28/J$17,0) -> 0 | AI28: =IFERROR(K28/K$17,0) -> 0 | AK28: =IFERROR(H28-G28,0) -> 0 | AL28: =IFERROR(I28-H28,0) -> 0 | AM28: =IFERROR(J28-I28,0) -> 0 | AN28: =IFERROR(K28-J28,0) -> 0 | AP28: =IFERROR((H28-G28)/G28,0) -> 0 | AQ28: =IFERROR((I28-H28)/H28,0) -> 0 | AR28: =IFERROR((J28-I28)/I28,0) -> 0 | AS28: =IFERROR((K28-J28)/J28,0) -> 0
A29: Cuentas por cobrar a largo plazo | G29: - | H29: - | I29: - | J29: - | K29: - | AE29: =IFERROR(G29/G$17,0) -> 0 | AF29: =IFERROR(H29/H$17,0) -> 0 | AG29: =IFERROR(I29/I$17,0) -> 0 | AH29: =IFERROR(J29/J$17,0) -> 0 | AI29: =IFERROR(K29/K$17,0) -> 0 | AK29: =IFERROR(H29-G29,0) -> 0 | AL29: =IFERROR(I29-H29,0) -> 0 | AM29: =IFERROR(J29-I29,0) -> 0 | AN29: =IFERROR(K29-J29,0) -> 0 | AP29: =IFERROR((H29-G29)/G29,0) -> 0 | AQ29: =IFERROR((I29-H29)/H29,0) -> 0 | AR29: =IFERROR((J29-I29)/I29,0) -> 0 | AS29: =IFERROR((K29-J29)/J29,0) -> 0
A30: Activos por impuestos diferidos a largo plazo | G30: 80 | H30: 87 | I30: 126 | J30: 140 | K30: 128 | AE30: =IFERROR(G30/G$17,0) -> 0.00096506466 | AF30: =IFERROR(H30/H$17,0) -> 0.001017532 | AG30: =IFERROR(I30/I$17,0) -> 0.0013922806 | AH30: =IFERROR(J30/J$17,0) -> 0.0014813091 | AI30: =IFERROR(K30/K$17,0) -> 0.0012847923 | AK30: =IFERROR(H30-G30,0) -> 7 | AL30: =IFERROR(I30-H30,0) -> 39 | AM30: =IFERROR(J30-I30,0) -> 14 | AN30: =IFERROR(K30-J30,0) -> -12 | AP30: =IFERROR((H30-G30)/G30,0) -> 0.0875 | AQ30: =IFERROR((I30-H30)/H30,0) -> 0.44827586 | AR30: =IFERROR((J30-I30)/I30,0) -> 0.11111111 | AS30: =IFERROR((K30-J30)/J30,0) -> -0.085714286
A31: Cargos diferidos a largo plazo | G31: - | H31: - | I31: - | J31: - | K31: - | AE31: =IFERROR(G31/G$17,0) -> 0 | AF31: =IFERROR(H31/H$17,0) -> 0 | AG31: =IFERROR(I31/I$17,0) -> 0 | AH31: =IFERROR(J31/J$17,0) -> 0 | AI31: =IFERROR(K31/K$17,0) -> 0 | AK31: =IFERROR(H31-G31,0) -> 0 | AL31: =IFERROR(I31-H31,0) -> 0 | AM31: =IFERROR(J31-I31,0) -> 0 | AN31: =IFERROR(K31-J31,0) -> 0 | AP31: =IFERROR((H31-G31)/G31,0) -> 0 | AQ31: =IFERROR((I31-H31)/H31,0) -> 0 | AR31: =IFERROR((J31-I31)/I31,0) -> 0 | AS31: =IFERROR((K31-J31)/J31,0) -> 0
A32: Total de otros activos a largo plazo | G32: 6514 | H32: 6518 | I32: 6906 | J32: 7266 | K32: 8019 | AE32: =IFERROR(G32/G$17,0) -> 0.07858039 | AF32: =IFERROR(H32/H$17,0) -> 0.076233027 | AG32: =IFERROR(I32/I$17,0) -> 0.076310235 | AH32: =IFERROR(J32/J$17,0) -> 0.07687994 | AI32: =IFERROR(K32/K$17,0) -> 0.080490229 | AK32: =IFERROR(H32-G32,0) -> 4 | AL32: =IFERROR(I32-H32,0) -> 388 | AM32: =IFERROR(J32-I32,0) -> 360 | AN32: =IFERROR(K32-J32,0) -> 753 | AP32: =IFERROR((H32-G32)/G32,0) -> 0.00061406202 | AQ32: =IFERROR((I32-H32)/H32,0) -> 0.059527462 | AR32: =IFERROR((J32-I32)/I32,0) -> 0.052128584 | AS32: =IFERROR((K32-J32)/J32,0) -> 0.10363336
A33: Total del pasivo corriente | G33: =SUM(G34,G35,G36,G37,G40) -> 15739 | H33: =SUM(H34,H35,H36,H37,H40) -> 20853 | I33: =SUM(I34,I35,I36,I37,I40) -> 23098 | J33: =SUM(J34,J35,J36,J37,J40) -> 26517 | K33: =SUM(K34,K35,K36,K37,K40) -> 35048 | AE33: =IFERROR(G33/G$17,0) -> 0.18986441 | AF33: =IFERROR(H33/H$17,0) -> 0.24389188 | AG33: =IFERROR(I33/I$17,0) -> 0.25522934 | AH33: =IFERROR(J33/J$17,0) -> 0.28057052 | AI33: =IFERROR(K33/K$17,0) -> 0.35179218 | AK33: =IFERROR(H33-G33,0) -> 5114 | AL33: =IFERROR(I33-H33,0) -> 2245 | AM33: =IFERROR(J33-I33,0) -> 3419 | AN33: =IFERROR(K33-J33,0) -> 8531 | AP33: =IFERROR((H33-G33)/G33,0) -> 0.32492534 | AQ33: =IFERROR((I33-H33)/H33,0) -> 0.10765837 | AR33: =IFERROR((J33-I33)/I33,0) -> 0.14802147 | AS33: =IFERROR((K33-J33)/J33,0) -> 0.32171814
A34: Total de cuentas por pagar | G34: 266 | H34: 340 | I34: 375 | J34: 479 | K34: 555 | AE34: =IFERROR(G34/G$17,0) -> 0.00320884 | AF34: =IFERROR(H34/H$17,0) -> 0.0039765617 | AG34: =IFERROR(I34/I$17,0) -> 0.0041436922 | AH34: =IFERROR(J34/J$17,0) -> 0.0050681931 | AI34: =IFERROR(K34/K$17,0) -> 0.005570779 | AK34: =IFERROR(H34-G34,0) -> 74 | AL34: =IFERROR(I34-H34,0) -> 35 | AM34: =IFERROR(J34-I34,0) -> 104 | AN34: =IFERROR(K34-J34,0) -> 76 | AP34: =IFERROR((H34-G34)/G34,0) -> 0.27819549 | AQ34: =IFERROR((I34-H34)/H34,0) -> 0.10294118 | AR34: =IFERROR((J34-I34)/I34,0) -> 0.27733333 | AS34: =IFERROR((K34-J34)/J34,0) -> 0.15866388
A35: Total de gastos devengados | G35: 3098 | H35: 4526 | I35: 4833 | J35: 5629 | K35: 6411 | AE35: =IFERROR(G35/G$17,0) -> 0.037372129 | AF35: =IFERROR(H35/H$17,0) -> 0.052935053 | AG35: =IFERROR(I35/I$17,0) -> 0.053403905 | AH35: =IFERROR(J35/J$17,0) -> 0.059559205 | AI35: =IFERROR(K35/K$17,0) -> 0.064350026 | AK35: =IFERROR(H35-G35,0) -> 1428 | AL35: =IFERROR(I35-H35,0) -> 307 | AM35: =IFERROR(J35-I35,0) -> 796 | AN35: =IFERROR(K35-J35,0) -> 782 | AP35: =IFERROR((H35-G35)/G35,0) -> 0.46094254 | AQ35: =IFERROR((I35-H35)/H35,0) -> 0.067830314 | AR35: =IFERROR((J35-I35)/I35,0) -> 0.16470101 | AS35: =IFERROR((K35-J35)/J35,0) -> 0.13892343
A36: Préstamos a corto plazo | G36: - | H36: - | I36: - | J36: - | K36: - | AE36: =IFERROR(G36/G$17,0) -> 0 | AF36: =IFERROR(H36/H$17,0) -> 0 | AG36: =IFERROR(I36/I$17,0) -> 0 | AH36: =IFERROR(J36/J$17,0) -> 0 | AI36: =IFERROR(K36/K$17,0) -> 0 | AK36: =IFERROR(H36-G36,0) -> 0 | AL36: =IFERROR(I36-H36,0) -> 0 | AM36: =IFERROR(J36-I36,0) -> 0 | AN36: =IFERROR(K36-J36,0) -> 0 | AP36: =IFERROR((H36-G36)/G36,0) -> 0 | AQ36: =IFERROR((I36-H36)/H36,0) -> 0 | AR36: =IFERROR((J36-I36)/I36,0) -> 0 | AS36: =IFERROR((K36-J36)/J36,0) -> 0
A37: Parte actual de la deuda a largo plazo/arrendamientos | G37: =SUM(G38,G39) -> 1102 | H37: =SUM(H38,H39) -> 2348 | I37: =SUM(I38,I39) -> 106 | J37: =SUM(J38,J39) -> 150 | K37: =SUM(K38,K39) -> 5719 | AE37: =IFERROR(G37/G$17,0) -> 0.013293766 | AF37: =IFERROR(H37/H$17,0) -> 0.027461667 | AG37: =IFERROR(I37/I$17,0) -> 0.0011712837 | AH37: =IFERROR(J37/J$17,0) -> 0.0015871168 | AI37: =IFERROR(K37/K$17,0) -> 0.057404117 | AK37: =IFERROR(H37-G37,0) -> 1246 | AL37: =IFERROR(I37-H37,0) -> -2242 | AM37: =IFERROR(J37-I37,0) -> 44 | AN37: =IFERROR(K37-J37,0) -> 5569 | AP37: =IFERROR((H37-G37)/G37,0) -> 1.1306715 | AQ37: =IFERROR((I37-H37)/H37,0) -> -0.9548552 | AR37: =IFERROR((J37-I37)/I37,0) -> 0.41509434 | AS37: =IFERROR((K37-J37)/J37,0) -> 37.126667
A38: Parte actual de la deuda a largo plazo | G38: 999 | H38: 2250 | I38: - | J38: - | K38: 5569 | AE38: =IFERROR(G38/G$17,0) -> 0.012051245 | AF38: =IFERROR(H38/H$17,0) -> 0.026315482 | AG38: =IFERROR(I38/I$17,0) -> 0 | AH38: =IFERROR(J38/J$17,0) -> 0 | AI38: =IFERROR(K38/K$17,0) -> 0.055898501 | AK38: =IFERROR(H38-G38,0) -> 1251 | AL38: =IFERROR(I38-H38,0) -> 0 | AM38: =IFERROR(J38-I38,0) -> 0 | AN38: =IFERROR(K38-J38,0) -> 0 | AP38: =IFERROR((H38-G38)/G38,0) -> 1.2522523 | AQ38: =IFERROR((I38-H38)/H38,0) -> 0 | AR38: =IFERROR((J38-I38)/I38,0) -> 0 | AS38: =IFERROR((K38-J38)/J38,0) -> 0
A39: Parte actual de arrendamientos | G39: 103 | H39: 98 | I39: 106 | J39: 150 | K39: 150 | AE39: =IFERROR(G39/G$17,0) -> 0.0012425207 | AF39: =IFERROR(H39/H$17,0) -> 0.0011461854 | AG39: =IFERROR(I39/I$17,0) -> 0.0011712837 | AH39: =IFERROR(J39/J$17,0) -> 0.0015871168 | AI39: =IFERROR(K39/K$17,0) -> 0.0015056159 | AK39: =IFERROR(H39-G39,0) -> -5 | AL39: =IFERROR(I39-H39,0) -> 8 | AM39: =IFERROR(J39-I39,0) -> 44 | AN39: =IFERROR(K39-J39,0) -> 0 | AP39: =IFERROR((H39-G39)/G39,0) -> -0.048543689 | AQ39: =IFERROR((I39-H39)/H39,0) -> 0.081632653 | AR39: =IFERROR((J39-I39)/I39,0) -> 0.41509434 | AS39: =IFERROR((K39-J39)/J39,0) -> 0
A40: Total de otros pasivos corrientes | G40: =SUM(G41,G42,G43) -> 11273 | H40: =SUM(H41,H42,H43) -> 13639 | I40: =SUM(I41,I42,I43) -> 17784 | J40: =SUM(J41,J42,J43) -> 20259 | K40: =SUM(K41,K42,K43) -> 22363 | AE40: =IFERROR(G40/G$17,0) -> 0.13598967 | AF40: =IFERROR(H40/H$17,0) -> 0.1595186 | AG40: =IFERROR(I40/I$17,0) -> 0.19651046 | AH40: =IFERROR(J40/J$17,0) -> 0.214356 | AI40: =IFERROR(K40/K$17,0) -> 0.22446726 | AK40: =IFERROR(H40-G40,0) -> 2366 | AL40: =IFERROR(I40-H40,0) -> 4145 | AM40: =IFERROR(J40-I40,0) -> 2475 | AN40: =IFERROR(K40-J40,0) -> 2104 | AP40: =IFERROR((H40-G40)/G40,0) -> 0.20988202 | AQ40: =IFERROR((I40-H40)/H40,0) -> 0.30390791 | AR40: =IFERROR((J40-I40)/I40,0) -> 0.13917004 | AS40: =IFERROR((K40-J40)/J40,0) -> 0.10385508
A41: Impuestos corrientes sobre la renta a pagar | G41: 325 | H41: 365 | I41: 1500 | J41: 577 | K41: 512 | AE41: =IFERROR(G41/G$17,0) -> 0.0039205752 | AF41: =IFERROR(H41/H$17,0) -> 0.0042689559 | AG41: =IFERROR(I41/I$17,0) -> 0.016574769 | AH41: =IFERROR(J41/J$17,0) -> 0.0061051095 | AI41: =IFERROR(K41/K$17,0) -> 0.0051391691 | AK41: =IFERROR(H41-G41,0) -> 40 | AL41: =IFERROR(I41-H41,0) -> 1135 | AM41: =IFERROR(J41-I41,0) -> -923 | AN41: =IFERROR(K41-J41,0) -> -65 | AP41: =IFERROR((H41-G41)/G41,0) -> 0.12307692 | AQ41: =IFERROR((I41-H41)/H41,0) -> 3.109589 | AR41: =IFERROR((J41-I41)/I41,0) -> -0.61533333 | AS41: =IFERROR((K41-J41)/J41,0) -> -0.11265165
A42: total de ingresos corrientes no devengados | G42: - | H42: - | I42: - | J42: - | K42: - | AE42: =IFERROR(G42/G$17,0) -> 0 | AF42: =IFERROR(H42/H$17,0) -> 0 | AG42: =IFERROR(I42/I$17,0) -> 0 | AH42: =IFERROR(J42/J$17,0) -> 0 | AI42: =IFERROR(K42/K$17,0) -> 0 | AK42: =IFERROR(H42-G42,0) -> 0 | AL42: =IFERROR(I42-H42,0) -> 0 | AM42: =IFERROR(J42-I42,0) -> 0 | AN42: =IFERROR(K42-J42,0) -> 0 | AP42: =IFERROR((H42-G42)/G42,0) -> 0 | AQ42: =IFERROR((I42-H42)/H42,0) -> 0 | AR42: =IFERROR((J42-I42)/I42,0) -> 0 | AS42: =IFERROR((K42-J42)/J42,0) -> 0
A43: Otros pasivos corrientes | G43: 10948 | H43: 13274 | I43: 16284 | J43: 19682 | K43: 21851 | AE43: =IFERROR(G43/G$17,0) -> 0.1320691 | AF43: =IFERROR(H43/H$17,0) -> 0.15524965 | AG43: =IFERROR(I43/I$17,0) -> 0.17993569 | AH43: =IFERROR(J43/J$17,0) -> 0.20825089 | AI43: =IFERROR(K43/K$17,0) -> 0.21932809 | AK43: =IFERROR(H43-G43,0) -> 2326 | AL43: =IFERROR(I43-H43,0) -> 3010 | AM43: =IFERROR(J43-I43,0) -> 3398 | AN43: =IFERROR(K43-J43,0) -> 2169 | AP43: =IFERROR((H43-G43)/G43,0) -> 0.2124589 | AQ43: =IFERROR((I43-H43)/H43,0) -> 0.22675908 | AR43: =IFERROR((J43-I43)/I43,0) -> 0.20867109 | AS43: =IFERROR((K43-J43)/J43,0) -> 0.11020222
A44: Pasivo total | G44: =SUM(G33,G46,G47,G48) -> 45307 | H44: =SUM(H33,H46,H47,H48) -> 49920 | I44: =SUM(I33,I46,I47,I48) -> 51766 | J44: =SUM(J33,J46,J47,J48) -> 55374 | K44: =SUM(K33,K46,K47,K48) -> 61718 | AE44: =IFERROR(G44/G$17,0) -> 0.54655231 | AF44: =IFERROR(H44/H$17,0) -> 0.58385282 | AG44: =IFERROR(I44/I$17,0) -> 0.57200632 | AH44: =IFERROR(J44/J$17,0) -> 0.58590005 | AI44: =IFERROR(K44/K$17,0) -> 0.6194907 | AK44: =IFERROR(H44-G44,0) -> 4613 | AL44: =IFERROR(I44-H44,0) -> 1846 | AM44: =IFERROR(J44-I44,0) -> 3608 | AN44: =IFERROR(K44-J44,0) -> 6344 | AP44: =IFERROR((H44-G44)/G44,0) -> 0.1018165 | AQ44: =IFERROR((I44-H44)/H44,0) -> 0.036979167 | AR44: =IFERROR((J44-I44)/I44,0) -> 0.069698258 | AS44: =IFERROR((K44-J44)/J44,0) -> 0.1145664
A45: Crecimiento del pasivo total | G45: 0.0134 | H45: =IFERROR((H44-G44)/G44,0) -> 0.1018165 | I45: =IFERROR((I44-H44)/H44,0) -> 0.036979167 | J45: =IFERROR((J44-I44)/I44,0) -> 0.069698258 | K45: =IFERROR((K44-J44)/J44,0) -> 0.1145664 | AE45: =IFERROR(G45/G$17,0) -> 1.6164833e-07 | AF45: =IFERROR(H45/H$17,0) -> 1.1908223e-06 | AG45: =IFERROR(I45/I$17,0) -> 4.0861409e-07 | AH45: =IFERROR(J45/J$17,0) -> 7.3746186e-07 | AI45: =IFERROR(K45/K$17,0) -> 1.1499534e-06 | AK45: =IFERROR(H45-G45,0) -> 0.088416496 | AL45: =IFERROR(I45-H45,0) -> -0.06483733 | AM45: =IFERROR(J45-I45,0) -> 0.032719091 | AN45: =IFERROR(K45-J45,0) -> 0.044868145 | AP45: =IFERROR((H45-G45)/G45,0) -> 6.598246 | AQ45: =IFERROR((I45-H45)/H45,0) -> -0.63680574 | AR45: =IFERROR((J45-I45)/I45,0) -> 0.88479795 | AS45: =IFERROR((K45-J45)/J45,0) -> 0.64374845
A46: Deuda a largo plazo | G46: 19978 | H46: 20522 | I46: 20777 | J46: 20836 | K46: 19602 | AE46: =IFERROR(G46/G$17,0) -> 0.24100077 | AF46: =IFERROR(H46/H$17,0) -> 0.24002058 | AG46: =IFERROR(I46/I$17,0) -> 0.22958265 | AH46: =IFERROR(J46/J$17,0) -> 0.22046111 | AI46: =IFERROR(K46/K$17,0) -> 0.19675389 | AK46: =IFERROR(H46-G46,0) -> 544 | AL46: =IFERROR(I46-H46,0) -> 255 | AM46: =IFERROR(J46-I46,0) -> 59 | AN46: =IFERROR(K46-J46,0) -> -1234 | AP46: =IFERROR((H46-G46)/G46,0) -> 0.027229953 | AQ46: =IFERROR((I46-H46)/H46,0) -> 0.01242569 | AR46: =IFERROR((J46-I46)/I46,0) -> 0.0028396785 | AS46: =IFERROR((K46-J46)/J46,0) -> -0.059224419
A47: Arrendamientos a largo plazo | G47: 471 | H47: 422 | I47: 412 | J47: 685 | K47: 763 | AE47: =IFERROR(G47/G$17,0) -> 0.0056818182 | AF47: =IFERROR(H47/H$17,0) -> 0.0049356148 | AG47: =IFERROR(I47/I$17,0) -> 0.0045525365 | AH47: =IFERROR(J47/J$17,0) -> 0.0072478336 | AI47: =IFERROR(K47/K$17,0) -> 0.0076585665 | AK47: =IFERROR(H47-G47,0) -> -49 | AL47: =IFERROR(I47-H47,0) -> -10 | AM47: =IFERROR(J47-I47,0) -> 273 | AN47: =IFERROR(K47-J47,0) -> 78 | AP47: =IFERROR((H47-G47)/G47,0) -> -0.10403397 | AQ47: =IFERROR((I47-H47)/H47,0) -> -0.023696682 | AR47: =IFERROR((J47-I47)/I47,0) -> 0.66262136 | AS47: =IFERROR((K47-J47)/J47,0) -> 0.11386861
A48: Total de otros pasivos | G48: =SUM(G49,G50,G51,G52) -> 9119 | H48: =SUM(H49,H50,H51,H52) -> 8123 | I48: =SUM(I49,I50,I51,I52) -> 7479 | J48: =SUM(J49,J50,J51,J52) -> 7336 | K48: =SUM(K49,K50,K51,K52) -> 6305 | AE48: =IFERROR(G48/G$17,0) -> 0.11000531 | AF48: =IFERROR(H48/H$17,0) -> 0.095004737 | AG48: =IFERROR(I48/I$17,0) -> 0.082641797 | AH48: =IFERROR(J48/J$17,0) -> 0.077620594 | AI48: =IFERROR(K48/K$17,0) -> 0.063286057 | AK48: =IFERROR(H48-G48,0) -> -996 | AL48: =IFERROR(I48-H48,0) -> -644 | AM48: =IFERROR(J48-I48,0) -> -143 | AN48: =IFERROR(K48-J48,0) -> -1031 | AP48: =IFERROR((H48-G48)/G48,0) -> -0.1092225 | AQ48: =IFERROR((I48-H48)/H48,0) -> -0.079281054 | AR48: =IFERROR((J48-I48)/I48,0) -> -0.019120203 | AS48: =IFERROR((K48-J48)/J48,0) -> -0.1405398
A49: Ingresos no devengados no corrientes | G49: - | H49: - | I49: - | J49: - | K49: - | AE49: =IFERROR(G49/G$17,0) -> 0 | AF49: =IFERROR(H49/H$17,0) -> 0 | AG49: =IFERROR(I49/I$17,0) -> 0 | AH49: =IFERROR(J49/J$17,0) -> 0 | AI49: =IFERROR(K49/K$17,0) -> 0 | AK49: =IFERROR(H49-G49,0) -> 0 | AL49: =IFERROR(I49-H49,0) -> 0 | AM49: =IFERROR(J49-I49,0) -> 0 | AN49: =IFERROR(K49-J49,0) -> 0 | AP49: =IFERROR((H49-G49)/G49,0) -> 0 | AQ49: =IFERROR((I49-H49)/H49,0) -> 0 | AR49: =IFERROR((J49-I49)/I49,0) -> 0 | AS49: =IFERROR((K49-J49)/J49,0) -> 0
A50: Pensiones y otras prestaciones posteriores a la jubilación | G50: - | H50: - | I50: - | J50: - | K50: - | AE50: =IFERROR(G50/G$17,0) -> 0 | AF50: =IFERROR(H50/H$17,0) -> 0 | AG50: =IFERROR(I50/I$17,0) -> 0 | AH50: =IFERROR(J50/J$17,0) -> 0 | AI50: =IFERROR(K50/K$17,0) -> 0 | AK50: =IFERROR(H50-G50,0) -> 0 | AL50: =IFERROR(I50-H50,0) -> 0 | AM50: =IFERROR(J50-I50,0) -> 0 | AN50: =IFERROR(K50-J50,0) -> 0 | AP50: =IFERROR((H50-G50)/G50,0) -> 0 | AQ50: =IFERROR((I50-H50)/H50,0) -> 0 | AR50: =IFERROR((J50-I50)/I50,0) -> 0 | AS50: =IFERROR((K50-J50)/J50,0) -> 0
A51: Pasivos por impuestos no corrientes diferidos | G51: 6128 | H51: 5332 | I51: 5114 | J51: 5301 | K51: 5549 | AE51: =IFERROR(G51/G$17,0) -> 0.073923953 | AF51: =IFERROR(H51/H$17,0) -> 0.062361844 | AG51: =IFERROR(I51/I$17,0) -> 0.056508912 | AH51: =IFERROR(J51/J$17,0) -> 0.056088709 | AI51: =IFERROR(K51/K$17,0) -> 0.055697753 | AK51: =IFERROR(H51-G51,0) -> -796 | AL51: =IFERROR(I51-H51,0) -> -218 | AM51: =IFERROR(J51-I51,0) -> 187 | AN51: =IFERROR(K51-J51,0) -> 248 | AP51: =IFERROR((H51-G51)/G51,0) -> -0.12989556 | AQ51: =IFERROR((I51-H51)/H51,0) -> -0.040885221 | AR51: =IFERROR((J51-I51)/I51,0) -> 0.036566289 | AS51: =IFERROR((K51-J51)/J51,0) -> 0.046783626
A52: Otros pasivos no corrientes | G52: 2991 | H52: 2791 | I52: 2365 | J52: 2035 | K52: 756 | AE52: =IFERROR(G52/G$17,0) -> 0.036081355 | AF52: =IFERROR(H52/H$17,0) -> 0.032642893 | AG52: =IFERROR(I52/I$17,0) -> 0.026132885 | AH52: =IFERROR(J52/J$17,0) -> 0.021531885 | AI52: =IFERROR(K52/K$17,0) -> 0.0075883044 | AK52: =IFERROR(H52-G52,0) -> -200 | AL52: =IFERROR(I52-H52,0) -> -426 | AM52: =IFERROR(J52-I52,0) -> -330 | AN52: =IFERROR(K52-J52,0) -> -1279 | AP52: =IFERROR((H52-G52)/G52,0) -> -0.066867268 | AQ52: =IFERROR((I52-H52)/H52,0) -> -0.15263346 | AR52: =IFERROR((J52-I52)/I52,0) -> -0.13953488 | AS52: =IFERROR((K52-J52)/J52,0) -> -0.62850123
A53: Patrimonio neto | G53: =SUM(G54,G58,G61,G62,G65) -> 37589 | H53: =SUM(H54,H58,H61,H62,H65) -> 35581 | I53: =SUM(I54,I58,I61,I62,I65) -> 38733 | J53: =SUM(J54,J58,J61,J62,J65) -> 39137 | K53: =SUM(K54,K58,K61,K62,K65) -> 37909 | AE53: =IFERROR(G53/G$17,0) -> 0.45344769 | AF53: =IFERROR(H53/H$17,0) -> 0.41614718 | AG53: =IFERROR(I53/I$17,0) -> 0.42799368 | AH53: =IFERROR(J53/J$17,0) -> 0.41409995 | AI53: =IFERROR(K53/K$17,0) -> 0.3805093 | AK53: =IFERROR(H53-G53,0) -> -2008 | AL53: =IFERROR(I53-H53,0) -> 3152 | AM53: =IFERROR(J53-I53,0) -> 404 | AN53: =IFERROR(K53-J53,0) -> -1228 | AP53: =IFERROR((H53-G53)/G53,0) -> -0.053419883 | AQ53: =IFERROR((I53-H53)/H53,0) -> 0.088586605 | AR53: =IFERROR((J53-I53)/I53,0) -> 0.010430382 | AS53: =IFERROR((K53-J53)/J53,0) -> -0.031376958
A54: Total de acciones preferentes | G54: 3080 | H54: 2324 | I54: 1698 | J54: 1031 | K54: 745 | AE54: =IFERROR(G54/G$17,0) -> 0.037154989 | AF54: =IFERROR(H54/H$17,0) -> 0.027180969 | AG54: =IFERROR(I54/I$17,0) -> 0.018762638 | AH54: =IFERROR(J54/J$17,0) -> 0.010908783 | AI54: =IFERROR(K54/K$17,0) -> 0.0074778925 | AK54: =IFERROR(H54-G54,0) -> -756 | AL54: =IFERROR(I54-H54,0) -> -626 | AM54: =IFERROR(J54-I54,0) -> -667 | AN54: =IFERROR(K54-J54,0) -> -286 | AP54: =IFERROR((H54-G54)/G54,0) -> -0.24545455 | AQ54: =IFERROR((I54-H54)/H54,0) -> -0.26936317 | AR54: =IFERROR((J54-I54)/I54,0) -> -0.39281508 | AS54: =IFERROR((K54-J54)/J54,0) -> -0.27740058
A55: Acciones preferentes reembolsables | G55: - | H55: - | I55: - | J55: - | K55: - | AE55: =IFERROR(G55/G$17,0) -> 0 | AF55: =IFERROR(H55/H$17,0) -> 0 | AG55: =IFERROR(I55/I$17,0) -> 0 | AH55: =IFERROR(J55/J$17,0) -> 0 | AI55: =IFERROR(K55/K$17,0) -> 0 | AK55: =IFERROR(H55-G55,0) -> 0 | AL55: =IFERROR(I55-H55,0) -> 0 | AM55: =IFERROR(J55-I55,0) -> 0 | AN55: =IFERROR(K55-J55,0) -> 0 | AP55: =IFERROR((H55-G55)/G55,0) -> 0 | AQ55: =IFERROR((I55-H55)/H55,0) -> 0 | AR55: =IFERROR((J55-I55)/I55,0) -> 0 | AS55: =IFERROR((K55-J55)/J55,0) -> 0
A56: Acciones preferentes no reembolsables | G56: - | H56: - | I56: - | J56: - | K56: - | AE56: =IFERROR(G56/G$17,0) -> 0 | AF56: =IFERROR(H56/H$17,0) -> 0 | AG56: =IFERROR(I56/I$17,0) -> 0 | AH56: =IFERROR(J56/J$17,0) -> 0 | AI56: =IFERROR(K56/K$17,0) -> 0 | AK56: =IFERROR(H56-G56,0) -> 0 | AL56: =IFERROR(I56-H56,0) -> 0 | AM56: =IFERROR(J56-I56,0) -> 0 | AN56: =IFERROR(K56-J56,0) -> 0 | AP56: =IFERROR((H56-G56)/G56,0) -> 0 | AQ56: =IFERROR((I56-H56)/H56,0) -> 0 | AR56: =IFERROR((J56-I56)/I56,0) -> 0 | AS56: =IFERROR((K56-J56)/J56,0) -> 0
A57: Acciones preferentes convertibles | G57: 3080 | H57: 2324 | I57: 1698 | J57: 1031 | K57: 745 | AE57: =IFERROR(G57/G$17,0) -> 0.037154989 | AF57: =IFERROR(H57/H$17,0) -> 0.027180969 | AG57: =IFERROR(I57/I$17,0) -> 0.018762638 | AH57: =IFERROR(J57/J$17,0) -> 0.010908783 | AI57: =IFERROR(K57/K$17,0) -> 0.0074778925 | AK57: =IFERROR(H57-G57,0) -> -756 | AL57: =IFERROR(I57-H57,0) -> -626 | AM57: =IFERROR(J57-I57,0) -> -667 | AN57: =IFERROR(K57-J57,0) -> -286 | AP57: =IFERROR((H57-G57)/G57,0) -> -0.24545455 | AQ57: =IFERROR((I57-H57)/H57,0) -> -0.26936317 | AR57: =IFERROR((J57-I57)/I57,0) -> -0.39281508 | AS57: =IFERROR((K57-J57)/J57,0) -> -0.27740058
A58: Acciones ordinarias y APIC | G58: 18855 | H58: 19545 | I58: 20452 | J58: 21229 | K58: 21934 | AE58: =IFERROR(G58/G$17,0) -> 0.22745368 | AF58: =IFERROR(H58/H$17,0) -> 0.22859382 | AG58: =IFERROR(I58/I$17,0) -> 0.22599145 | AH58: =IFERROR(J58/J$17,0) -> 0.22461936 | AI58: =IFERROR(K58/K$17,0) -> 0.2201612 | AK58: =IFERROR(H58-G58,0) -> 690 | AL58: =IFERROR(I58-H58,0) -> 907 | AM58: =IFERROR(J58-I58,0) -> 777 | AN58: =IFERROR(K58-J58,0) -> 705 | AP58: =IFERROR((H58-G58)/G58,0) -> 0.036595068 | AQ58: =IFERROR((I58-H58)/H58,0) -> 0.04640573 | AR58: =IFERROR((J58-I58)/I58,0) -> 0.037991394 | AS58: =IFERROR((K58-J58)/J58,0) -> 0.033209289
A59: Total de acciones ordinarias | G59: 18855 | H59: 19545 | I59: - | J59: - | K59: - | AE59: =IFERROR(G59/G$17,0) -> 0.22745368 | AF59: =IFERROR(H59/H$17,0) -> 0.22859382 | AG59: =IFERROR(I59/I$17,0) -> 0 | AH59: =IFERROR(J59/J$17,0) -> 0 | AI59: =IFERROR(K59/K$17,0) -> 0 | AK59: =IFERROR(H59-G59,0) -> 690 | AL59: =IFERROR(I59-H59,0) -> 0 | AM59: =IFERROR(J59-I59,0) -> 0 | AN59: =IFERROR(K59-J59,0) -> 0 | AP59: =IFERROR((H59-G59)/G59,0) -> 0.036595068 | AQ59: =IFERROR((I59-H59)/H59,0) -> 0 | AR59: =IFERROR((J59-I59)/I59,0) -> 0 | AS59: =IFERROR((K59-J59)/J59,0) -> 0
A60: Capital pagado adicional | G60: - | H60: - | I60: 20452 | J60: 21229 | K60: 21934 | AE60: =IFERROR(G60/G$17,0) -> 0 | AF60: =IFERROR(H60/H$17,0) -> 0 | AG60: =IFERROR(I60/I$17,0) -> 0.22599145 | AH60: =IFERROR(J60/J$17,0) -> 0.22461936 | AI60: =IFERROR(K60/K$17,0) -> 0.2201612 | AK60: =IFERROR(H60-G60,0) -> 0 | AL60: =IFERROR(I60-H60,0) -> 0 | AM60: =IFERROR(J60-I60,0) -> 777 | AN60: =IFERROR(K60-J60,0) -> 705 | AP60: =IFERROR((H60-G60)/G60,0) -> 0 | AQ60: =IFERROR((I60-H60)/H60,0) -> 0 | AR60: =IFERROR((J60-I60)/I60,0) -> 0.037991394 | AS60: =IFERROR((K60-J60)/J60,0) -> 0.033209289
A61: Ganancias retenidas | G61: 15351 | H61: 16116 | I61: 18040 | J61: 17289 | K61: 15106 | AE61: =IFERROR(G61/G$17,0) -> 0.18518384 | AF61: =IFERROR(H61/H$17,0) -> 0.18848902 | AG61: =IFERROR(I61/I$17,0) -> 0.19933922 | AH61: =IFERROR(J61/J$17,0) -> 0.18293109 | AI61: =IFERROR(K61/K$17,0) -> 0.15162556 | AK61: =IFERROR(H61-G61,0) -> 765 | AL61: =IFERROR(I61-H61,0) -> 1924 | AM61: =IFERROR(J61-I61,0) -> -751 | AN61: =IFERROR(K61-J61,0) -> -2183 | AP61: =IFERROR((H61-G61)/G61,0) -> 0.049833887 | AQ61: =IFERROR((I61-H61)/H61,0) -> 0.11938446 | AR61: =IFERROR((J61-I61)/I61,0) -> -0.041629712 | AS61: =IFERROR((K61-J61)/J61,0) -> -0.12626526
A62: Acciones propias y otras | G62: 303 | H62: -2404 | I62: -1457 | J62: -412 | K62: 124 | AE62: =IFERROR(G62/G$17,0) -> 0.0036551824 | AF62: =IFERROR(H62/H$17,0) -> -0.02811663 | AG62: =IFERROR(I62/I$17,0) -> -0.016099625 | AH62: =IFERROR(J62/J$17,0) -> -0.0043592809 | AI62: =IFERROR(K62/K$17,0) -> 0.0012446425 | AK62: =IFERROR(H62-G62,0) -> -2707 | AL62: =IFERROR(I62-H62,0) -> 947 | AM62: =IFERROR(J62-I62,0) -> 1045 | AN62: =IFERROR(K62-J62,0) -> 536 | AP62: =IFERROR((H62-G62)/G62,0) -> -8.9339934 | AQ62: =IFERROR((I62-H62)/H62,0) -> -0.39392679 | AR62: =IFERROR((J62-I62)/I62,0) -> -0.71722718 | AS62: =IFERROR((K62-J62)/J62,0) -> -1.3009709
A63: Acciones propias | G63: - | H63: - | I63: - | J63: - | K63: - | AE63: =IFERROR(G63/G$17,0) -> 0 | AF63: =IFERROR(H63/H$17,0) -> 0 | AG63: =IFERROR(I63/I$17,0) -> 0 | AH63: =IFERROR(J63/J$17,0) -> 0 | AI63: =IFERROR(K63/K$17,0) -> 0 | AK63: =IFERROR(H63-G63,0) -> 0 | AL63: =IFERROR(I63-H63,0) -> 0 | AM63: =IFERROR(J63-I63,0) -> 0 | AN63: =IFERROR(K63-J63,0) -> 0 | AP63: =IFERROR((H63-G63)/G63,0) -> 0 | AQ63: =IFERROR((I63-H63)/H63,0) -> 0 | AR63: =IFERROR((J63-I63)/I63,0) -> 0 | AS63: =IFERROR((K63-J63)/J63,0) -> 0
A64: Ingresos globales y otros | G64: 303 | H64: -2404 | I64: -1457 | J64: -412 | K64: 124 | AE64: =IFERROR(G64/G$17,0) -> 0.0036551824 | AF64: =IFERROR(H64/H$17,0) -> -0.02811663 | AG64: =IFERROR(I64/I$17,0) -> -0.016099625 | AH64: =IFERROR(J64/J$17,0) -> -0.0043592809 | AI64: =IFERROR(K64/K$17,0) -> 0.0012446425 | AK64: =IFERROR(H64-G64,0) -> -2707 | AL64: =IFERROR(I64-H64,0) -> 947 | AM64: =IFERROR(J64-I64,0) -> 1045 | AN64: =IFERROR(K64-J64,0) -> 536 | AP64: =IFERROR((H64-G64)/G64,0) -> -8.9339934 | AQ64: =IFERROR((I64-H64)/H64,0) -> -0.39392679 | AR64: =IFERROR((J64-I64)/I64,0) -> -0.71722718 | AS64: =IFERROR((K64-J64)/J64,0) -> -1.3009709
A65: Intereses minoritarios | G65: - | H65: - | I65: - | J65: - | K65: - | AE65: =IFERROR(G65/G$17,0) -> 0 | AF65: =IFERROR(H65/H$17,0) -> 0 | AG65: =IFERROR(I65/I$17,0) -> 0 | AH65: =IFERROR(J65/J$17,0) -> 0 | AI65: =IFERROR(K65/K$17,0) -> 0 | AK65: =IFERROR(H65-G65,0) -> 0 | AL65: =IFERROR(I65-H65,0) -> 0 | AM65: =IFERROR(J65-I65,0) -> 0 | AN65: =IFERROR(K65-J65,0) -> 0 | AP65: =IFERROR((H65-G65)/G65,0) -> 0 | AQ65: =IFERROR((I65-H65)/H65,0) -> 0 | AR65: =IFERROR((J65-I65)/I65,0) -> 0 | AS65: =IFERROR((K65-J65)/J65,0) -> 0
A66: Total del pasivo y del patrimonio neto | G66: =SUM(G44,G53) -> 82896 | H66: =SUM(H44,H53) -> 85501 | I66: =SUM(I44,I53) -> 90499 | J66: =SUM(J44,J53) -> 94511 | K66: =SUM(K44,K53) -> 99627 | AE66: =IFERROR(G66/G$17,0) -> 1 | AF66: =IFERROR(H66/H$17,0) -> 1 | AG66: =IFERROR(I66/I$17,0) -> 1 | AH66: =IFERROR(J66/J$17,0) -> 1 | AI66: =IFERROR(K66/K$17,0) -> 1 | AK66: =IFERROR(H66-G66,0) -> 2605 | AL66: =IFERROR(I66-H66,0) -> 4998 | AM66: =IFERROR(J66-I66,0) -> 4012 | AN66: =IFERROR(K66-J66,0) -> 5116 | AP66: =IFERROR((H66-G66)/G66,0) -> 0.031424918 | AQ66: =IFERROR((I66-H66)/H66,0) -> 0.058455457 | AR66: =IFERROR((J66-I66)/I66,0) -> 0.044331982 | AS66: =IFERROR((K66-J66)/J66,0) -> 0.054131265
A68: Deuda total | G68: =SUM(G38,G39,G46,G47) -> 21551 | H68: =SUM(H38,H39,H46,H47) -> 23292 | I68: =SUM(I38,I39,I46,I47) -> 21295 | J68: =SUM(J38,J39,J46,J47) -> 21671 | K68: =SUM(K38,K39,K46,K47) -> 26084 | AE68: =IFERROR(G68/G$17,0) -> 0.25997636 | AF68: =IFERROR(H68/H$17,0) -> 0.27241787 | AG68: =IFERROR(I68/I$17,0) -> 0.23530647 | AH68: =IFERROR(J68/J$17,0) -> 0.22929606 | AI68: =IFERROR(K68/K$17,0) -> 0.26181658 | AK68: =IFERROR(H68-G68,0) -> 1741 | AL68: =IFERROR(I68-H68,0) -> -1997 | AM68: =IFERROR(J68-I68,0) -> 376 | AN68: =IFERROR(K68-J68,0) -> 4413 | AP68: =IFERROR((H68-G68)/G68,0) -> 0.080785114 | AQ68: =IFERROR((I68-H68)/H68,0) -> -0.085737592 | AR68: =IFERROR((J68-I68)/I68,0) -> 0.017656727 | AS68: =IFERROR((K68-J68)/J68,0) -> 0.2036362
A69: Crecimiento de la deuda total | G69: -0.1254 | H69: =IFERROR((H68-G68)/G68,0) -> 0.080785114 | I69: =IFERROR((I68-H68)/H68,0) -> -0.085737592 | J69: =IFERROR((J68-I68)/I68,0) -> 0.017656727 | K69: =IFERROR((K68-J68)/J68,0) -> 0.2036362 | AE69: =IFERROR(G69/G$17,0) -> -1.5127389e-06 | AF69: =IFERROR(H69/H$17,0) -> 9.4484409e-07 | AG69: =IFERROR(I69/I$17,0) -> -9.4738718e-07 | AH69: =IFERROR(J69/J$17,0) -> 1.8682192e-07 | AI69: =IFERROR(K69/K$17,0) -> 2.043986e-06 | AK69: =IFERROR(H69-G69,0) -> 0.20618511 | AL69: =IFERROR(I69-H69,0) -> -0.16652271 | AM69: =IFERROR(J69-I69,0) -> 0.10339432 | AN69: =IFERROR(K69-J69,0) -> 0.18597947 | AP69: =IFERROR((H69-G69)/G69,0) -> -1.6442194 | AQ69: =IFERROR((I69-H69)/H69,0) -> -2.0613043 | AR69: =IFERROR((J69-I69)/I69,0) -> -1.2059392 | AS69: =IFERROR((K69-J69)/J69,0) -> 10.533066

Sheet PyG
A1: ESTADO DE RESULTADO | G1: 2021 | H1: 2022 | I1: 2023 | J1: 2024 | K1: 2025 | AA1: ANÁLISIS VERTICAL (% de Ingresos Totales) | AG1: ANÁLISIS HORIZONTAL - Variación absoluta | AL1: ANÁLISIS HORIZONTAL - Variación %
G2: 46295 | H2: 46295 | I2: 46295 | J2: 46295 | K2: 46295 | AA2: 2021 | AB2: 2022 | AC2: 2023 | AD2: 2024 | AE2: 2025 | AG2: 2022/2021 | AH2: 2023/2022 | AI2: 2024/2023 | AJ2: 2025/2024 | AL2: 2022/2021 | AM2: 2023/2022 | AN2: 2024/2023 | AO2: 2025/2024
A3: Ingresos totales | G3: 24105 | H3: 29310 | I3: 32653 | J3: 35926 | K3: 40000 | AA3: =IFERROR(G3/G$3,0) -> 1 | AB3: =IFERROR(H3/H$3,0) -> 1 | AC3: =IFERROR(I3/I$3,0) -> 1 | AD3: =IFERROR(J3/J$3,0) -> 1 | AE3: =IFERROR(K3/K$3,0) -> 1 | AG3: =IFERROR(H3-G3,0) -> 5205 | AH3: =IFERROR(I3-H3,0) -> 3343 | AI3: =IFERROR(J3-I3,0) -> 3273 | AJ3: =IFERROR(K3-J3,0) -> 4074 | AL3: =IFERROR((H3-G3)/G3,0) -> 0.2159303 | AM3: =IFERROR((I3-H3)/H3,0) -> 0.11405664 | AN3: =IFERROR((J3-I3)/I3,0) -> 0.10023581 | AO3: =IFERROR((K3-J3)/J3,0) -> 0.11339977
A4: Crecimiento de los ingresos totales | G4: 0.1034 | H4: =IFERROR((H3-G3)/G3,0) -> 0.2159303 | I4: =IFERROR((I3-H3)/H3,0) -> 0.11405664 | J4: =IFERROR((J3-I3)/I3,0) -> 0.10023581 | K4: =IFERROR((K3-J3)/J3,0) -> 0.11339977 | AA4: =IFERROR(G4/G$3,0) -> 4.2895665e-06 | AB4: =IFERROR(H4/H$3,0) -> 7.3671206e-06 | AC4: =IFERROR(I4/I$3,0) -> 3.492991e-06 | AD4: =IFERROR(J4/J$3,0) -> 2.7900633e-06 | AE4: =IFERROR(K4/K$3,0) -> 2.8349942e-06 | AG4: =IFERROR(H4-G4,0) -> 0.1125303 | AH4: =IFERROR(I4-H4,0) -> -0.10187367 | AI4: =IFERROR(J4-I4,0) -> -0.013820823 | AJ4: =IFERROR(K4-J4,0) -> 0.013163953 | AL4: =IFERROR((H4-G4)/G4,0) -> 1.0883008 | AM4: =IFERROR((I4-H4)/H4,0) -> -0.47178959 | AN4: =IFERROR((J4-I4)/I4,0) -> -0.12117509 | AO4: =IFERROR((K4-J4)/J4,0) -> 0.13132984
A5: Coste de los ingresos | G5: 730 | H5: 743 | I5: 736 | J5: 778 | K5: 894 | AA5: =IFERROR(G5/G$3,0) -> 0.030284173 | AB5: =IFERROR(H5/H$3,0) -> 0.02534971 | AC5: =IFERROR(I5/I$3,0) -> 0.022540042 | AD5: =IFERROR(J5/J$3,0) -> 0.021655625 | AE5: =IFERROR(K5/K$3,0) -> 0.02235 | AG5: =IFERROR(H5-G5,0) -> 13 | AH5: =IFERROR(I5-H5,0) -> -7 | AI5: =IFERROR(J5-I5,0) -> 42 | AJ5: =IFERROR(K5-J5,0) -> 116 | AL5: =IFERROR((H5-G5)/G5,0) -> 0.017808219 | AM5: =IFERROR((I5-H5)/H5,0) -> -0.0094212651 | AN5: =IFERROR((J5-I5)/I5,0) -> 0.057065217 | AO5: =IFERROR((K5-J5)/J5,0) -> 0.14910026
A6: Beneficio bruto | G6: =IFERROR(G3-G5,0) -> 23375 | H6: =IFERROR(H3-H5,0) -> 28567 | I6: =IFERROR(I3-I5,0) -> 31917 | J6: =IFERROR(J3-J5,0) -> 35148 | K6: =IFERROR(K3-K5,0) -> 39106 | AA6: =IFERROR(G6/G$3,0) -> 0.96971583 | AB6: =IFERROR(H6/H$3,0) -> 0.97465029 | AC6: =IFERROR(I6/I$3,0) -> 0.97745996 | AD6: =IFERROR(J6/J$3,0) -> 0.97834437 | AE6: =IFERROR(K6/K$3,0) -> 0.97765 | AG6: =IFERROR(H6-G6,0) -> 5192 | AH6: =IFERROR(I6-H6,0) -> 3350 | AI6: =IFERROR(J6-I6,0) -> 3231 | AJ6: =IFERROR(K6-J6,0) -> 3958 | AL6: =IFERROR((H6-G6)/G6,0) -> 0.22211765 | AM6: =IFERROR((I6-H6)/H6,0) -> 0.11726818 | AN6: =IFERROR((J6-I6)/I6,0) -> 0.10123132 | AO6: =IFERROR((K6-J6)/J6,0) -> 0.11260954
A7: Crecimiento del beneficio bruto | G7: 0.1068 | H7: =IFERROR((H6-G6)/G6,0) -> 0.22211765 | I7: =IFERROR((I6-H6)/H6,0) -> 0.11726818 | J7: =IFERROR((J6-I6)/I6,0) -> 0.10123132 | K7: =IFERROR((K6-J6)/J6,0) -> 0.11260954 | AA7: =IFERROR(G7/G$3,0) -> 4.4306161e-06 | AB7: =IFERROR(H7/H$3,0) -> 7.5782206e-06 | AC7: =IFERROR(I7/I$3,0) -> 3.5913446e-06 | AD7: =IFERROR(J7/J$3,0) -> 2.8177732e-06 | AE7: =IFERROR(K7/K$3,0) -> 2.8152384e-06 | AG7: =IFERROR(H7-G7,0) -> 0.11531765 | AH7: =IFERROR(I7-H7,0) -> -0.10484947 | AI7: =IFERROR(J7-I7,0) -> -0.016036858 | AJ7: =IFERROR(K7-J7,0) -> 0.011378218 | AL7: =IFERROR((H7-G7)/G7,0) -> 1.0797532 | AM7: =IFERROR((I7-H7)/H7,0) -> -0.47204476 | AN7: =IFERROR((J7-I7)/I7,0) -> -0.13675371 | AO7: =IFERROR((K7-J7)/J7,0) -> 0.1123982
A8: Margen de beneficio bruto % | G8: =IFERROR(G6/G3,0) -> 0.96971583 | H8: =IFERROR(H6/H3,0) -> 0.97465029 | I8: =IFERROR(I6/I3,0) -> 0.97745996 | J8: =IFERROR(J6/J3,0) -> 0.97834437 | K8: =IFERROR(K6/K3,0) -> 0.97765 | AA8: =IFERROR(G8/G$3,0) -> 4.0228825e-05 | AB8: =IFERROR(H8/H$3,0) -> 3.3253166e-05 | AC8: =IFERROR(I8/I$3,0) -> 2.9934767e-05 | AD8: =IFERROR(J8/J$3,0) -> 2.723221e-05 | AE8: =IFERROR(K8/K$3,0) -> 2.444125e-05 | AG8: =IFERROR(H8-G8,0) -> 0.0049344634 | AH8: =IFERROR(I8-H8,0) -> 0.0028096677 | AI8: =IFERROR(J8-I8,0) -> 0.00088441681 | AJ8: =IFERROR(K8-J8,0) -> -0.00069437455 | AL8: =IFERROR((H8-G8)/G8,0) -> 0.0050885664 | AM8: =IFERROR((I8-H8)/H8,0) -> 0.0028827445 | AN8: =IFERROR((J8-I8)/I8,0) -> 0.0009048113 | AO8: =IFERROR((K8-J8)/J8,0) -> -0.00070974451
A9: Total de otros gastos operativos | G9: 7568 | H9: 8886 | I9: 9990 | J9: 11152 | K9: 12298 | AA9: =IFERROR(G9/G$3,0) -> 0.31395976 | AB9: =IFERROR(H9/H$3,0) -> 0.30317298 | AC9: =IFERROR(I9/I$3,0) -> 0.30594432 | AD9: =IFERROR(J9/J$3,0) -> 0.31041585 | AE9: =IFERROR(K9/K$3,0) -> 0.30745 | AG9: =IFERROR(H9-G9,0) -> 1318 | AH9: =IFERROR(I9-H9,0) -> 1104 | AI9: =IFERROR(J9-I9,0) -> 1162 | AJ9: =IFERROR(K9-J9,0) -> 1146 | AL9: =IFERROR((H9-G9)/G9,0) -> 0.17415433 | AM9: =IFERROR((I9-H9)/H9,0) -> 0.12424038 | AN9: =IFERROR((J9-I9)/I9,0) -> 0.11631632 | AO9: =IFERROR((K9-J9)/J9,0) -> 0.10276184
A10: Crecmiento total de otros gastos operativos | G10: 0.0821 | H10: =IFERROR((H9-G9)/G9,0) -> 0.17415433 | I10: =IFERROR((I9-H9)/H9,0) -> 0.12424038 | J10: =IFERROR((J9-I9)/I9,0) -> 0.11631632 | K10: =IFERROR((K9-J9)/J9,0) -> 0.10276184 | AA10: =IFERROR(G10/G$3,0) -> 3.4059324e-06 | AB10: =IFERROR(H10/H$3,0) -> 5.941806e-06 | AC10: =IFERROR(I10/I$3,0) -> 3.8048687e-06 | AD10: =IFERROR(J10/J$3,0) -> 3.237664e-06 | AE10: =IFERROR(K10/K$3,0) -> 2.5690459e-06 | AG10: =IFERROR(H10-G10,0) -> 0.092054334 | AH10: =IFERROR(I10-H10,0) -> -0.049913956 | AI10: =IFERROR(J10-I10,0) -> -0.0079240618 | AJ10: =IFERROR(K10-J10,0) -> -0.01355448 | AL10: =IFERROR((H10-G10)/G10,0) -> 1.1212465 | AM10: =IFERROR((I10-H10)/H10,0) -> -0.2866076 | AN10: =IFERROR((J10-I10)/I10,0) -> -0.063780084 | AO10: =IFERROR((K10-J10)/J10,0) -> -0.1165312
A11: Gastos de I+D | G11: - | H11: - | I11: - | J11: - | K11: - | AA11: =IFERROR(G11/G$3,0) -> 0 | AB11: =IFERROR(H11/H$3,0) -> 0 | AC11: =IFERROR(I11/I$3,0) -> 0 | AD11: =IFERROR(J11/J$3,0) -> 0 | AE11: =IFERROR(K11/K$3,0) -> 0 | AG11: =IFERROR(H11-G11,0) -> 0 | AH11: =IFERROR(I11-H11,0) -> 0 | AI11: =IFERROR(J11-I11,0) -> 0 | AJ11: =IFERROR(K11-J11,0) -> 0 | AL11: =IFERROR((H11-G11)/G11,0) -> 0 | AM11: =IFERROR((I11-H11)/H11,0) -> 0 | AN11: =IFERROR((J11-I11)/I11,0) -> 0 | AO11: =IFERROR((K11-J11)/J11,0) -> 0
A12: Gastos de venta, generales y administrativos | G12: 6612 | H12: 8025 | I12: 9047 | J12: 10118 | K12: 11078 | AA12: =IFERROR(G12/G$3,0) -> 0.27429994 | AB12: =IFERROR(H12/H$3,0) -> 0.27379734 | AC12: =IFERROR(I12/I$3,0) -> 0.27706489 | AD12: =IFERROR(J12/J$3,0) -> 0.28163447 | AE12: =IFERROR(K12/K$3,0) -> 0.27695 | AG12: =IFERROR(H12-G12,0) -> 1413 | AH12: =IFERROR(I12-H12,0) -> 1022 | AI12: =IFERROR(J12-I12,0) -> 1071 | AJ12: =IFERROR(K12-J12,0) -> 960 | AL12: =IFERROR((H12-G12)/G12,0) -> 0.21370236 | AM12: =IFERROR((I12-H12)/H12,0) -> 0.12735202 | AN12: =IFERROR((J12-I12)/I12,0) -> 0.11838178 | AO12: =IFERROR((K12-J12)/J12,0) -> 0.094880411
A13: Otros gastos operativos | G13: 152 | H13: - | I13: - | J13: - | K13: - | AA13: =IFERROR(G13/G$3,0) -> 0.0063057457 | AB13: =IFERROR(H13/H$3,0) -> 0 | AC13: =IFERROR(I13/I$3,0) -> 0 | AD13: =IFERROR(J13/J$3,0) -> 0 | AE13: =IFERROR(K13/K$3,0) -> 0 | AG13: =IFERROR(H13-G13,0) -> 0 | AH13: =IFERROR(I13-H13,0) -> 0 | AI13: =IFERROR(J13-I13,0) -> 0 | AJ13: =IFERROR(K13-J13,0) -> 0 | AL13: =IFERROR((H13-G13)/G13,0) -> 0 | AM13: =IFERROR((I13-H13)/H13,0) -> 0 | AN13: =IFERROR((J13-I13)/I13,0) -> 0 | AO13: =IFERROR((K13-J13)/J13,0) -> 0
A14: Margen neto | G14: =IFERROR(G6-G9,0) -> 15807 | H14: =IFERROR(H6-H9,0) -> 19681 | I14: =IFERROR(I6-I9,0) -> 21927 | J14: =IFERROR(J6-J9,0) -> 23996 | K14: =IFERROR(K6-K9,0) -> 26808 | AA14: =IFERROR(G14/G$3,0) -> 0.65575607 | AB14: =IFERROR(H14/H$3,0) -> 0.67147731 | AC14: =IFERROR(I14/I$3,0) -> 0.67151563 | AD14: =IFERROR(J14/J$3,0) -> 0.66792852 | AE14: =IFERROR(K14/K$3,0) -> 0.6702 | AG14: =IFERROR(H14-G14,0) -> 3874 | AH14: =IFERROR(I14-H14,0) -> 2246 | AI14: =IFERROR(J14-I14,0) -> 2069 | AJ14: =IFERROR(K14-J14,0) -> 2812 | AL14: =IFERROR((H14-G14)/G14,0) -> 0.24508129 | AM14: =IFERROR((I14-H14)/H14,0) -> 0.11412022 | AN14: =IFERROR((J14-I14)/I14,0) -> 0.094358553 | AO14: =IFERROR((K14-J14)/J14,0) -> 0.1171862
A15: Crecimiento del margen neto | G15: 0.1191 | H15: =IFERROR((H14-G14)/G14,0) -> 0.24508129 | I15: =IFERROR((I14-H14)/H14,0) -> 0.11412022 | J15: =IFERROR((J14-I14)/I14,0) -> 0.094358553 | K15: =IFERROR((K14-J14)/J14,0) -> 0.1171862 | AA15: =IFERROR(G15/G$3,0) -> 4.9408836e-06 | AB15: =IFERROR(H15/H$3,0) -> 8.3616954e-06 | AC15: =IFERROR(I15/I$3,0) -> 3.4949382e-06 | AD15: =IFERROR(J15/J$3,0) -> 2.6264698e-06 | AE15: =IFERROR(K15/K$3,0) -> 2.9296549e-06 | AG15: =IFERROR(H15-G15,0) -> 0.12598129 | AH15: =IFERROR(I15-H15,0) -> -0.13096108 | AI15: =IFERROR(J15-I15,0) -> -0.019761664 | AJ15: =IFERROR(K15-J15,0) -> 0.022827644 | AL15: =IFERROR((H15-G15)/G15,0) -> 1.0577774 | AM15: =IFERROR((I15-H15)/H15,0) -> -0.5343577 | AN15: =IFERROR((J15-I15)/I15,0) -> -0.17316532 | AO15: =IFERROR((K15-J15)/J15,0) -> 0.24192448
A16: Margen EBIT % | G16: =IFERROR(G14/G3,0) -> 0.65575607 | H16: =IFERROR(H14/H3,0) -> 0.67147731 | I16: =IFERROR(I14/I3,0) -> 0.67151563 | J16: =IFERROR(J14/J3,0) -> 0.66792852 | K16: =IFERROR(K14/K3,0) -> 0.6702 | AA16: =IFERROR(G16/G$3,0) -> 2.7204151e-05 | AB16: =IFERROR(H16/H$3,0) -> 2.2909495e-05 | AC16: =IFERROR(I16/I$3,0) -> 2.0565205e-05 | AD16: =IFERROR(J16/J$3,0) -> 1.8591786e-05 | AE16: =IFERROR(K16/K$3,0) -> 1.6755e-05 | AG16: =IFERROR(H16-G16,0) -> 0.015721244 | AH16: =IFERROR(I16-H16,0) -> 3.8322594e-05 | AI16: =IFERROR(J16-I16,0) -> -0.0035871144 | AJ16: =IFERROR(K16-J16,0) -> 0.0022714803 | AL16: =IFERROR((H16-G16)/G16,0) -> 0.023974226 | AM16: =IFERROR((I16-H16)/H16,0) -> 5.7072061e-05 | AN16: =IFERROR((J16-I16)/I16,0) -> -0.0053418181 | AO16: =IFERROR((K16-J16)/J16,0) -> 0.0034007835
A17: Gastos netos por intereses | G17: =IFERROR(SUM(G19,G20),0) -> -513 | H17: =IFERROR(SUM(H19,H20),0) -> -469 | I17: =IFERROR(SUM(I19,I20),0) -> 101 | J17: =IFERROR(SUM(J19,J20),0) -> 351 | K17: =IFERROR(SUM(K19,K20),0) -> 202 | AA17: =IFERROR(G17/G$3,0) -> -0.021281892 | AB17: =IFERROR(H17/H$3,0) -> -0.016001365 | AC17: =IFERROR(I17/I$3,0) -> 0.0030931308 | AD17: =IFERROR(J17/J$3,0) -> 0.0097700829 | AE17: =IFERROR(K17/K$3,0) -> 0.00505 | AG17: =IFERROR(H17-G17,0) -> 44 | AH17: =IFERROR(I17-H17,0) -> 570 | AI17: =IFERROR(J17-I17,0) -> 250 | AJ17: =IFERROR(K17-J17,0) -> -149 | AL17: =IFERROR((H17-G17)/G17,0) -> -0.085769981 | AM17: =IFERROR((I17-H17)/H17,0) -> -1.2153518 | AN17: =IFERROR((J17-I17)/I17,0) -> 2.4752475 | AO17: =IFERROR((K17-J17)/J17,0) -> -0.42450142
A18: Crecimiento de gastos netos por intereses | G18: -0.1766 | H18: =IFERROR((H17-G17)/G17,0) -> -0.085769981 | I18: =IFERROR((I17-H17)/H17,0) -> -1.2153518 | J18: =IFERROR((J17-I17)/I17,0) -> 2.4752475 | K18: =IFERROR((K17-J17)/J17,0) -> -0.42450142 | AA18: =IFERROR(G18/G$3,0) -> -7.3262809e-06 | AB18: =IFERROR(H18/H$3,0) -> -2.9263044e-06 | AC18: =IFERROR(I18/I$3,0) -> -3.7220219e-05 | AD18: =IFERROR(J18/J$3,0) -> 6.88985e-05 | AE18: =IFERROR(K18/K$3,0) -> -1.0612536e-05 | AG18: =IFERROR(H18-G18,0) -> 0.090830019 | AH18: =IFERROR(I18-H18,0) -> -1.1295818 | AI18: =IFERROR(J18-I18,0) -> 3.6905993 | AJ18: =IFERROR(K18-J18,0) -> -2.8997489 | AL18: =IFERROR((H18-G18)/G18,0) -> -0.51432627 | AM18: =IFERROR((I18-H18)/H18,0) -> 13.169897 | AN18: =IFERROR((J18-I18)/I18,0) -> -3.036651 | AO18: =IFERROR((K18-J18)/J18,0) -> -1.1714986
A19: Total de gastos de intereses | G19: -513 | H19: -538 | I19: -644 | J19: -641 | K19: -589 | AA19: =IFERROR(G19/G$3,0) -> -0.021281892 | AB19: =IFERROR(H19/H$3,0) -> -0.01835551 | AC19: =IFERROR(I19/I$3,0) -> -0.019722537 | AD19: =IFERROR(J19/J$3,0) -> -0.017842231 | AE19: =IFERROR(K19/K$3,0) -> -0.014725 | AG19: =IFERROR(H19-G19,0) -> -25 | AH19: =IFERROR(I19-H19,0) -> -106 | AI19: =IFERROR(J19-I19,0) -> 3 | AJ19: =IFERROR(K19-J19,0) -> 52 | AL19: =IFERROR((H19-G19)/G19,0) -> 0.048732943 | AM19: =IFERROR((I19-H19)/H19,0) -> 0.19702602 | AN19: =IFERROR((J19-I19)/I19,0) -> -0.0046583851 | AO19: =IFERROR((K19-J19)/J19,0) -> -0.081123245
A20: Ingresos por intereses e inversiones | G20: - | H20: 69 | I20: 745 | J20: 992 | K20: 791 | AA20: =IFERROR(G20/G$3,0) -> 0 | AB20: =IFERROR(H20/H$3,0) -> 0.0023541453 | AC20: =IFERROR(I20/I$3,0) -> 0.022815668 | AD20: =IFERROR(J20/J$3,0) -> 0.027612314 | AE20: =IFERROR(K20/K$3,0) -> 0.019775 | AG20: =IFERROR(H20-G20,0) -> 0 | AH20: =IFERROR(I20-H20,0) -> 676 | AI20: =IFERROR(J20-I20,0) -> 247 | AJ20: =IFERROR(K20-J20,0) -> -201 | AL20: =IFERROR((H20-G20)/G20,0) -> 0 | AM20: =IFERROR((I20-H20)/H20,0) -> 9.7971014 | AN20: =IFERROR((J20-I20)/I20,0) -> 0.33154362 | AO20: =IFERROR((K20-J20)/J20,0) -> -0.20262097
A21: Total de otros gastos no operativos | G21: 25 | H21: 88 | I21: 18 | J21: 14 | K21: 49 | AA21: =IFERROR(G21/G$3,0) -> 0.0010371292 | AB21: =IFERROR(H21/H$3,0) -> 0.0030023883 | AC21: =IFERROR(I21/I$3,0) -> 0.00055125103 | AD21: =IFERROR(J21/J$3,0) -> 0.00038968992 | AE21: =IFERROR(K21/K$3,0) -> 0.001225 | AG21: =IFERROR(H21-G21,0) -> 63 | AH21: =IFERROR(I21-H21,0) -> -70 | AI21: =IFERROR(J21-I21,0) -> -4 | AJ21: =IFERROR(K21-J21,0) -> 35 | AL21: =IFERROR((H21-G21)/G21,0) -> 2.52 | AM21: =IFERROR((I21-H21)/H21,0) -> -0.79545455 | AN21: =IFERROR((J21-I21)/I21,0) -> -0.22222222 | AO21: =IFERROR((K21-J21)/J21,0) -> 2.5
A22: EBT excepto elementos no habituales | G22: =IFERROR(SUM(G14,G17,G21),0) -> 15319 | H22: =IFERROR(SUM(H14,H17,H21),0) -> 19300 | I22: =IFERROR(SUM(I14,I17,I21),0) -> 22046 | J22: =IFERROR(SUM(J14,J17,J21),0) -> 24361 | K22: =IFERROR(SUM(K14,K17,K21),0) -> 27059 | AA22: =IFERROR(G22/G$3,0) -> 0.6355113 | AB22: =IFERROR(H22/H$3,0) -> 0.65847834 | AC22: =IFERROR(I22/I$3,0) -> 0.67516002 | AD22: =IFERROR(J22/J$3,0) -> 0.67808829 | AE22: =IFERROR(K22/K$3,0) -> 0.676475 | AG22: =IFERROR(H22-G22,0) -> 3981 | AH22: =IFERROR(I22-H22,0) -> 2746 | AI22: =IFERROR(J22-I22,0) -> 2315 | AJ22: =IFERROR(K22-J22,0) -> 2698 | AL22: =IFERROR((H22-G22)/G22,0) -> 0.25987336 | AM22: =IFERROR((I22-H22)/H22,0) -> 0.14227979 | AN22: =IFERROR((J22-I22)/I22,0) -> 0.10500771 | AO22: =IFERROR((K22-J22)/J22,0) -> 0.11075079
A23: Ganancia (pérdida) de la venta de activos | G23: - | H23: - | I23: - | J23: - | K23: - | AA23: =IFERROR(G23/G$3,0) -> 0 | AB23: =IFERROR(H23/H$3,0) -> 0 | AC23: =IFERROR(I23/I$3,0) -> 0 | AD23: =IFERROR(J23/J$3,0) -> 0 | AE23: =IFERROR(K23/K$3,0) -> 0 | AG23: =IFERROR(H23-G23,0) -> 0 | AH23: =IFERROR(I23-H23,0) -> 0 | AI23: =IFERROR(J23-I23,0) -> 0 | AJ23: =IFERROR(K23-J23,0) -> 0 | AL23: =IFERROR((H23-G23)/G23,0) -> 0 | AM23: =IFERROR((I23-H23)/H23,0) -> 0 | AN23: =IFERROR((J23-I23)/I23,0) -> 0 | AO23: =IFERROR((K23-J23)/J23,0) -> 0
A24: Total de otras partidas no habituales | G24: -3 | H24: -868 | I24: -927 | J24: -401 | K24: -2601 | AA24: =IFERROR(G24/G$3,0) -> -0.00012445551 | AB24: =IFERROR(H24/H$3,0) -> -0.029614466 | AC24: =IFERROR(I24/I$3,0) -> -0.028389428 | AD24: =IFERROR(J24/J$3,0) -> -0.011161833 | AE24: =IFERROR(K24/K$3,0) -> -0.065025 | AG24: =IFERROR(H24-G24,0) -> -865 | AH24: =IFERROR(I24-H24,0) -> -59 | AI24: =IFERROR(J24-I24,0) -> 526 | AJ24: =IFERROR(K24-J24,0) -> -2200 | AL24: =IFERROR((H24-G24)/G24,0) -> 288.33333 | AM24: =IFERROR((I24-H24)/H24,0) -> 0.06797235 | AN24: =IFERROR((J24-I24)/I24,0) -> -0.56742179 | AO24: =IFERROR((K24-J24)/J24,0) -> 5.4862843
A25: EBT incluyendo las partidas inusuales | G25: 16063 | H25: 18136 | I25: 21037 | J25: 23916 | K25: 24194 | AA25: =IFERROR(G25/G$3,0) -> 0.66637627 | AB25: =IFERROR(H25/H$3,0) -> 0.61876493 | AC25: =IFERROR(I25/I$3,0) -> 0.64425933 | AD25: =IFERROR(J25/J$3,0) -> 0.66570172 | AE25: =IFERROR(K25/K$3,0) -> 0.60485 | AG25: =IFERROR(H25-G25,0) -> 2073 | AH25: =IFERROR(I25-H25,0) -> 2901 | AI25: =IFERROR(J25-I25,0) -> 2879 | AJ25: =IFERROR(K25-J25,0) -> 278 | AL25: =IFERROR((H25-G25)/G25,0) -> 0.12905435 | AM25: =IFERROR((I25-H25)/H25,0) -> 0.15995809 | AN25: =IFERROR((J25-I25)/I25,0) -> 0.13685411 | AO25: =IFERROR((K25-J25)/J25,0) -> 0.011624017
A26: Crecimiento del EBT incluidas las partidas inusuales | G26: 0.1648 | H26: =IFERROR((H25-G25)/G25,0) -> 0.12905435 | I26: =IFERROR((I25-H25)/H25,0) -> 0.15995809 | J26: =IFERROR((J25-I25)/I25,0) -> 0.13685411 | K26: =IFERROR((K25-J25)/J25,0) -> 0.011624017 | AA26: =IFERROR(G26/G$3,0) -> 6.8367559e-06 | AB26: =IFERROR(H26/H$3,0) -> 4.4030825e-06 | AC26: =IFERROR(I26/I$3,0) -> 4.8987258e-06 | AD26: =IFERROR(J26/J$3,0) -> 3.8093335e-06 | AE26: =IFERROR(K26/K$3,0) -> 2.9060043e-07 | AG26: =IFERROR(H26-G26,0) -> -0.035745651 | AH26: =IFERROR(I26-H26,0) -> 0.030903746 | AI26: =IFERROR(J26-I26,0) -> -0.02310398 | AJ26: =IFERROR(K26-J26,0) -> -0.1252301 | AL26: =IFERROR((H26-G26)/G26,0) -> -0.21690323 | AM26: =IFERROR((I26-H26)/H26,0) -> 0.23946303 | AN26: =IFERROR((J26-I26)/I26,0) -> -0.14443771 | AO26: =IFERROR((K26-J26)/J26,0) -> -0.91506271
A27: Margen del EBT incluidas las partidas inusuales | G27: =IFERROR(G25/G3,0) -> 0.66637627 | H27: =IFERROR(H25/H3,0) -> 0.61876493 | I27: =IFERROR(I25/I3,0) -> 0.64425933 | J27: =IFERROR(J25/J3,0) -> 0.66570172 | K27: =IFERROR(K25/K3,0) -> 0.60485 | AA27: =IFERROR(G27/G$3,0) -> 2.7644732e-05 | AB27: =IFERROR(H27/H$3,0) -> 2.1111052e-05 | AC27: =IFERROR(I27/I$3,0) -> 1.9730479e-05 | AD27: =IFERROR(J27/J$3,0) -> 1.8529803e-05 | AE27: =IFERROR(K27/K$3,0) -> 1.512125e-05 | AG27: =IFERROR(H27-G27,0) -> -0.047611344 | AH27: =IFERROR(I27-H27,0) -> 0.025494406 | AI27: =IFERROR(J27-I27,0) -> 0.021442387 | AJ27: =IFERROR(K27-J27,0) -> -0.06085172 | AL27: =IFERROR((H27-G27)/G27,0) -> -0.071448138 | AM27: =IFERROR((I27-H27)/H27,0) -> 0.041202087 | AN27: =IFERROR((J27-I27)/I27,0) -> 0.03328223 | AO27: =IFERROR((K27-J27)/J27,0) -> -0.091409889
A28: Impuesto sobre la renta | G28: 3752 | H28: 3179 | I28: 3764 | J28: 4173 | K28: 4136 | AA28: =IFERROR(G28/G$3,0) -> 0.15565235 | AB28: =IFERROR(H28/H$3,0) -> 0.10846128 | AC28: =IFERROR(I28/I$3,0) -> 0.11527272 | AD28: =IFERROR(J28/J$3,0) -> 0.11615543 | AE28: =IFERROR(K28/K$3,0) -> 0.1034 | AG28: =IFERROR(H28-G28,0) -> -573 | AH28: =IFERROR(I28-H28,0) -> 585 | AI28: =IFERROR(J28-I28,0) -> 409 | AJ28: =IFERROR(K28-J28,0) -> -37 | AL28: =IFERROR((H28-G28)/G28,0) -> -0.15271855 | AM28: =IFERROR((I28-H28)/H28,0) -> 0.18402013 | AN28: =IFERROR((J28-I28)/I28,0) -> 0.108661 | AO28: =IFERROR((K28-J28)/J28,0) -> -0.0088665229
A29: Beneficios netos para la empresa | G29: =IFERROR(G25-G28,0) -> 12311 | H29: =IFERROR(H25-H28,0) -> 14957 | I29: =IFERROR(I25-I28,0) -> 17273 | J29: =IFERROR(J25-J28,0) -> 19743 | K29: =IFERROR(K25-K28,0) -> 20058 | AA29: =IFERROR(G29/G$3,0) -> 0.51072392 | AB29: =IFERROR(H29/H$3,0) -> 0.51030365 | AC29: =IFERROR(I29/I$3,0) -> 0.52898662 | AD29: =IFERROR(J29/J$3,0) -> 0.54954629 | AE29: =IFERROR(K29/K$3,0) -> 0.50145 | AG29: =IFERROR(H29-G29,0) -> 2646 | AH29: =IFERROR(I29-H29,0) -> 2316 | AI29: =IFERROR(J29-I29,0) -> 2470 | AJ29: =IFERROR(K29-J29,0) -> 315 | AL29: =IFERROR((H29-G29)/G29,0) -> 0.21492974 | AM29: =IFERROR((I29-H29)/H29,0) -> 0.15484389 | AN29: =IFERROR((J29-I29)/I29,0) -> 0.14299774 | AO29: =IFERROR((K29-J29)/J29,0) -> 0.015955022
A30: Intereses minoritarios | G30: - | H30: - | I30: - | J30: - | K30: - | AA30: =IFERROR(G30/G$3,0) -> 0 | AB30: =IFERROR(H30/H$3,0) -> 0 | AC30: =IFERROR(I30/I$3,0) -> 0 | AD30: =IFERROR(J30/J$3,0) -> 0 | AE30: =IFERROR(K30/K$3,0) -> 0 | AG30: =IFERROR(H30-G30,0) -> 0 | AH30: =IFERROR(I30-H30,0) -> 0 | AI30: =IFERROR(J30-I30,0) -> 0 | AJ30: =IFERROR(K30-J30,0) -> 0 | AL30: =IFERROR((H30-G30)/G30,0) -> 0 | AM30: =IFERROR((I30-H30)/H30,0) -> 0 | AN30: =IFERROR((J30-I30)/I30,0) -> 0 | AO30: =IFERROR((K30-J30)/J30,0) -> 0
A31: Beneficio neto | G31: =IFERROR(G29-SUM(G30),0) -> 12311 | H31: =IFERROR(H29-SUM(H30),0) -> 14957 | I31: =IFERROR(I29-SUM(I30),0) -> 17273 | J31: =IFERROR(J29-SUM(J30),0) -> 19743 | K31: =IFERROR(K29-SUM(K30),0) -> 20058 | AA31: =IFERROR(G31/G$3,0) -> 0.51072392 | AB31: =IFERROR(H31/H$3,0) -> 0.51030365 | AC31: =IFERROR(I31/I$3,0) -> 0.52898662 | AD31: =IFERROR(J31/J$3,0) -> 0.54954629 | AE31: =IFERROR(K31/K$3,0) -> 0.50145 | AG31: =IFERROR(H31-G31,0) -> 2646 | AH31: =IFERROR(I31-H31,0) -> 2316 | AI31: =IFERROR(J31-I31,0) -> 2470 | AJ31: =IFERROR(K31-J31,0) -> 315 | AL31: =IFERROR((H31-G31)/G31,0) -> 0.21492974 | AM31: =IFERROR((I31-H31)/H31,0) -> 0.15484389 | AN31: =IFERROR((J31-I31)/I31,0) -> 0.14299774 | AO31: =IFERROR((K31-J31)/J31,0) -> 0.015955022
A32: Crecimiento del beneficio neto | G32: 0.133 | H32: =IFERROR((H31-G31)/G31,0) -> 0.21492974 | I32: =IFERROR((I31-H31)/H31,0) -> 0.15484389 | J32: =IFERROR((J31-I31)/I31,0) -> 0.14299774 | K32: =IFERROR((K31-J31)/J31,0) -> 0.015955022 | AA32: =IFERROR(G32/G$3,0) -> 5.5175275e-06 | AB32: =IFERROR(H32/H$3,0) -> 7.3329832e-06 | AC32: =IFERROR(I32/I$3,0) -> 4.7421029e-06 | AD32: =IFERROR(J32/J$3,0) -> 3.9803413e-06 | AE32: =IFERROR(K32/K$3,0) -> 3.9887555e-07 | AG32: =IFERROR(H32-G32,0) -> 0.081929738 | AH32: =IFERROR(I32-H32,0) -> -0.060085852 | AI32: =IFERROR(J32-I32,0) -> -0.011846144 | AJ32: =IFERROR(K32-J32,0) -> -0.12704272 | AL32: =IFERROR((H32-G32)/G32,0) -> 0.61601306 | AM32: =IFERROR((I32-H32)/H32,0) -> -0.27956044 | AN32: =IFERROR((J32-I32)/I32,0) -> -0.076503787 | AO32: =IFERROR((K32-J32)/J32,0) -> -0.88842466
A33: Margen del beneficio neto % | G33: =IFERROR(G31/G3,0) -> 0.51072392 | H33: =IFERROR(H31/H3,0) -> 0.51030365 | I33: =IFERROR(I31/I3,0) -> 0.52898662 | J33: =IFERROR(J31/J3,0) -> 0.54954629 | K33: =IFERROR(K31/K3,0) -> 0.50145 | AA33: =IFERROR(G33/G$3,0) -> 2.1187468e-05 | AB33: =IFERROR(H33/H$3,0) -> 1.7410565e-05 | AC33: =IFERROR(I33/I$3,0) -> 1.6200246e-05 | AD33: =IFERROR(J33/J$3,0) -> 1.5296618e-05 | AE33: =IFERROR(K33/K$3,0) -> 1.253625e-05 | AG33: =IFERROR(H33-G33,0) -> -0.00042026557 | AH33: =IFERROR(I33-H33,0) -> 0.018682966 | AI33: =IFERROR(J33-I33,0) -> 0.020559673 | AJ33: =IFERROR(K33-J33,0) -> -0.04809629 | AL33: =IFERROR((H33-G33)/G33,0) -> -0.0008228821 | AM33: =IFERROR((I33-H33)/H33,0) -> 0.036611469 | AN33: =IFERROR((J33-I33)/I33,0) -> 0.038866149 | AO33: =IFERROR((K33-J33)/J33,0) -> -0.087519997
A34: Dividendo preferente y otros ajustes | G34: 303 | H34: 327 | I34: 284 | J34: 286 | K34: 205 | AA34: =IFERROR(G34/G$3,0) -> 0.012570006 | AB34: =IFERROR(H34/H$3,0) -> 0.011156602 | AC34: =IFERROR(I34/I$3,0) -> 0.0086975163 | AD34: =IFERROR(J34/J$3,0) -> 0.0079608083 | AE34: =IFERROR(K34/K$3,0) -> 0.005125 | AG34: =IFERROR(H34-G34,0) -> 24 | AH34: =IFERROR(I34-H34,0) -> -43 | AI34: =IFERROR(J34-I34,0) -> 2 | AJ34: =IFERROR(K34-J34,0) -> -81 | AL34: =IFERROR((H34-G34)/G34,0) -> 0.079207921 | AM34: =IFERROR((I34-H34)/H34,0) -> -0.13149847 | AN34: =IFERROR((J34-I34)/I34,0) -> 0.0070422535 | AO34: =IFERROR((K34-J34)/J34,0) -> -0.28321678
A35: Beneficio neto sobre ingresos ordinarios | G35: =IFERROR(G31-G34,0) -> 12008 | H35: =IFERROR(H31-H34,0) -> 14630 | I35: =IFERROR(I31-I34,0) -> 16989 | J35: =IFERROR(J31-J34,0) -> 19457 | K35: =IFERROR(K31-K34,0) -> 19853 | AA35: =IFERROR(G35/G$3,0) -> 0.49815391 | AB35: =IFERROR(H35/H$3,0) -> 0.49914705 | AC35: =IFERROR(I35/I$3,0) -> 0.5202891 | AD35: =IFERROR(J35/J$3,0) -> 0.54158548 | AE35: =IFERROR(K35/K$3,0) -> 0.496325 | AG35: =IFERROR(H35-G35,0) -> 2622 | AH35: =IFERROR(I35-H35,0) -> 2359 | AI35: =IFERROR(J35-I35,0) -> 2468 | AJ35: =IFERROR(K35-J35,0) -> 396 | AL35: =IFERROR((H35-G35)/G35,0) -> 0.21835443 | AM35: =IFERROR((I35-H35)/H35,0) -> 0.16124402 | AN35: =IFERROR((J35-I35)/I35,0) -> 0.14527047 | AO35: =IFERROR((K35-J35)/J35,0) -> 0.020352572
A36: BPA básico: Crecimiento de actividades continuadas | G36: 5.66 | H36: 7.56 | I36: 8.33 | J36: 9.78 | K36: 10.23 | AA36: =IFERROR(G36/G$3,0) -> 0.00023480606 | AB36: =IFERROR(H36/H$3,0) -> 0.00025793245 | AC36: =IFERROR(I36/I$3,0) -> 0.00025510673 | AD36: =IFERROR(J36/J$3,0) -> 0.00027222624 | AE36: =IFERROR(K36/K$3,0) -> 0.00025575 | AG36: =IFERROR(H36-G36,0) -> 1.9 | AH36: =IFERROR(I36-H36,0) -> 0.77 | AI36: =IFERROR(J36-I36,0) -> 1.45 | AJ36: =IFERROR(K36-J36,0) -> 0.45 | AL36: =IFERROR((H36-G36)/G36,0) -> 0.33568905 | AM36: =IFERROR((I36-H36)/H36,0) -> 0.10185185 | AN36: =IFERROR((J36-I36)/I36,0) -> 0.17406963 | AO36: =IFERROR((K36-J36)/J36,0) -> 0.04601227
A37: BPA básico: crecimiento de actividades continuadas | G37: 0.1538 | H37: =IFERROR((H36-G36)/G36,0) -> 0.33568905 | I37: =IFERROR((I36-H36)/H36,0) -> 0.10185185 | J37: =IFERROR((J36-I36)/I36,0) -> 0.17406963 | K37: =IFERROR((K36-J36)/J36,0) -> 0.04601227 | AA37: =IFERROR(G37/G$3,0) -> 6.380419e-06 | AB37: =IFERROR(H37/H$3,0) -> 1.1453055e-05 | AC37: =IFERROR(I37/I$3,0) -> 3.1192188e-06 | AD37: =IFERROR(J37/J$3,0) -> 4.8452271e-06 | AE37: =IFERROR(K37/K$3,0) -> 1.1503067e-06 | AG37: =IFERROR(H37-G37,0) -> 0.18188905 | AH37: =IFERROR(I37-H37,0) -> -0.23383719 | AI37: =IFERROR(J37-I37,0) -> 0.072217776 | AJ37: =IFERROR(K37-J37,0) -> -0.12805736 | AL37: =IFERROR((H37-G37)/G37,0) -> 1.1826336 | AM37: =IFERROR((I37-H37)/H37,0) -> -0.69658869 | AN37: =IFERROR((J37-I37)/I37,0) -> 0.70904726 | AO37: =IFERROR((K37-J37)/J37,0) -> -0.73566744
A38: BPA diluido: Crecimiento de actividades continuadas | G38: 5.63 | H38: 7 | I38: 8.28 | J38: 9.73 | K38: 10.2 | AA38: =IFERROR(G38/G$3,0) -> 0.0002335615 | AB38: =IFERROR(H38/H$3,0) -> 0.00023882634 | AC38: =IFERROR(I38/I$3,0) -> 0.00025357548 | AD38: =IFERROR(J38/J$3,0) -> 0.00027083449 | AE38: =IFERROR(K38/K$3,0) -> 0.000255 | AG38: =IFERROR(H38-G38,0) -> 1.37 | AH38: =IFERROR(I38-H38,0) -> 1.28 | AI38: =IFERROR(J38-I38,0) -> 1.45 | AJ38: =IFERROR(K38-J38,0) -> 0.47 | AL38: =IFERROR((H38-G38)/G38,0) -> 0.24333925 | AM38: =IFERROR((I38-H38)/H38,0) -> 0.18285714 | AN38: =IFERROR((J38-I38)/I38,0) -> 0.17512077 | AO38: =IFERROR((K38-J38)/J38,0) -> 0.048304214
A39: BPA diluido: Actividades continuadas | G39: 0.1511 | H39: =IFERROR((H38-G38)/G38,0) -> 0.24333925 | I39: =IFERROR((I38-H38)/H38,0) -> 0.18285714 | J39: =IFERROR((J38-I38)/I38,0) -> 0.17512077 | K39: =IFERROR((K38-J38)/J38,0) -> 0.048304214 | AA39: =IFERROR(G39/G$3,0) -> 6.268409e-06 | AB39: =IFERROR(H39/H$3,0) -> 8.3022605e-06 | AC39: =IFERROR(I39/I$3,0) -> 5.6000105e-06 | AD39: =IFERROR(J39/J$3,0) -> 4.8744857e-06 | AE39: =IFERROR(K39/K$3,0) -> 1.2076053e-06 | AG39: =IFERROR(H39-G39,0) -> 0.092239254 | AH39: =IFERROR(I39-H39,0) -> -0.060482111 | AI39: =IFERROR(J39-I39,0) -> -0.0077363699 | AJ39: =IFERROR(K39-J39,0) -> -0.12681656 | AL39: =IFERROR((H39-G39)/G39,0) -> 0.61045171 | AM39: =IFERROR((I39-H39)/H39,0) -> -0.24855057 | AN39: =IFERROR((J39-I39)/I39,0) -> -0.042308273 | AO39: =IFERROR((K39-J39)/J39,0) -> -0.72416628
A40: Promedio ponderado básico de acciones en circulación | G40: 2120.6 | H40: 1936 | I40: 2038.95 | J40: 1989.72 | K40: 1940.45 | AA40: =IFERROR(G40/G$3,0) -> 0.087973449 | AB40: =IFERROR(H40/H$3,0) -> 0.066052542 | AC40: =IFERROR(I40/I$3,0) -> 0.062442961 | AD40: =IFERROR(J40/J$3,0) -> 0.055383845 | AE40: =IFERROR(K40/K$3,0) -> 0.04851125 | AG40: =IFERROR(H40-G40,0) -> -184.6 | AH40: =IFERROR(I40-H40,0) -> 102.95 | AI40: =IFERROR(J40-I40,0) -> -49.23 | AJ40: =IFERROR(K40-J40,0) -> -49.27 | AL40: =IFERROR((H40-G40)/G40,0) -> -0.087050835 | AM40: =IFERROR((I40-H40)/H40,0) -> 0.053176653 | AN40: =IFERROR((J40-I40)/I40,0) -> -0.02414478 | AO40: =IFERROR((K40-J40)/J40,0) -> -0.024762278
A41: Promedio ponderado diluido de acciones en circulación | G41: 2188 | H41: 2136 | I41: 2085 | J41: 2029 | K41: 1966 | AA41: =IFERROR(G41/G$3,0) -> 0.09076955 | AB41: =IFERROR(H41/H$3,0) -> 0.072876151 | AC41: =IFERROR(I41/I$3,0) -> 0.063853245 | AD41: =IFERROR(J41/J$3,0) -> 0.056477203 | AE41: =IFERROR(K41/K$3,0) -> 0.04915 | AG41: =IFERROR(H41-G41,0) -> -52 | AH41: =IFERROR(I41-H41,0) -> -51 | AI41: =IFERROR(J41-I41,0) -> -56 | AJ41: =IFERROR(K41-J41,0) -> -63 | AL41: =IFERROR((H41-G41)/G41,0) -> -0.023765996 | AM41: =IFERROR((I41-H41)/H41,0) -> -0.023876404 | AN41: =IFERROR((J41-I41)/I41,0) -> -0.026858513 | AO41: =IFERROR((K41-J41)/J41,0) -> -0.031049778
A42: Dividendo por acción | G42: 1.34 | H42: 1.58 | I42: 1.87 | J42: 2.15 | K42: 2.44 | AA42: =IFERROR(G42/G$3,0) -> 5.5590127e-05 | AB42: =IFERROR(H42/H$3,0) -> 5.3906517e-05 | AC42: =IFERROR(I42/I$3,0) -> 5.7268857e-05 | AD42: =IFERROR(J42/J$3,0) -> 5.9845237e-05 | AE42: =IFERROR(K42/K$3,0) -> 6.1e-05 | AG42: =IFERROR(H42-G42,0) -> 0.24 | AH42: =IFERROR(I42-H42,0) -> 0.29 | AI42: =IFERROR(J42-I42,0) -> 0.28 | AJ42: =IFERROR(K42-J42,0) -> 0.29 | AL42: =IFERROR((H42-G42)/G42,0) -> 0.17910448 | AM42: =IFERROR((I42-H42)/H42,0) -> 0.1835443 | AN42: =IFERROR((J42-I42)/I42,0) -> 0.14973262 | AO42: =IFERROR((K42-J42)/J42,0) -> 0.13488372
A43: Crecimiento del dividendo por acción | G43: 0.0943 | H43: =IFERROR((H42-G42)/G42,0) -> 0.17910448 | I43: =IFERROR((I42-H42)/H42,0) -> 0.1835443 | J43: =IFERROR((J42-I42)/I42,0) -> 0.14973262 | K43: =IFERROR((K42-J42)/J42,0) -> 0.13488372 | AA43: =IFERROR(G43/G$3,0) -> 3.9120514e-06 | AB43: =IFERROR(H43/H$3,0) -> 6.1106952e-06 | AC43: =IFERROR(I43/I$3,0) -> 5.6210548e-06 | AD43: =IFERROR(J43/J$3,0) -> 4.1678066e-06 | AE43: =IFERROR(K43/K$3,0) -> 3.372093e-06 | AG43: =IFERROR(H43-G43,0) -> 0.084804478 | AH43: =IFERROR(I43-H43,0) -> 0.0044398262 | AI43: =IFERROR(J43-I43,0) -> -0.033811683 | AJ43: =IFERROR(K43-J43,0) -> -0.014848899 | AL43: =IFERROR((H43-G43)/G43,0) -> 0.89930517 | AM43: =IFERROR((I43-H43)/H43,0) -> 0.02478903 | AN43: =IFERROR((J43-I43)/I43,0) -> -0.18421538 | AO43: =IFERROR((K43-J43)/J43,0) -> -0.099169435
A45: EBITDA | G45: 16611 | H45: 20542 | I45: 22870 | J45: 25030 | K45: 28028 | AA45: =IFERROR(G45/G$3,0) -> 0.68911014 | AB45: =IFERROR(H45/H$3,0) -> 0.70085295 | AC45: =IFERROR(I45/I$3,0) -> 0.70039506 | AD45: =IFERROR(J45/J$3,0) -> 0.6967099 | AE45: =IFERROR(K45/K$3,0) -> 0.7007 | AG45: =IFERROR(H45-G45,0) -> 3931 | AH45: =IFERROR(I45-H45,0) -> 2328 | AI45: =IFERROR(J45-I45,0) -> 2160 | AJ45: =IFERROR(K45-J45,0) -> 2998 | AL45: =IFERROR((H45-G45)/G45,0) -> 0.23665041 | AM45: =IFERROR((I45-H45)/H45,0) -> 0.11332879 | AN45: =IFERROR((J45-I45)/I45,0) -> 0.094446874 | AO45: =IFERROR((K45-J45)/J45,0) -> 0.11977627
A46: Crecimiento del EBITDA | G46: 0.1154 | H46: =IFERROR((H45-G45)/G45,0) -> 0.23665041 | I46: =IFERROR((I45-H45)/H45,0) -> 0.11332879 | J46: =IFERROR((J45-I45)/I45,0) -> 0.094446874 | K46: =IFERROR((K45-J45)/J45,0) -> 0.11977627 | AA46: =IFERROR(G46/G$3,0) -> 4.7873885e-06 | AB46: =IFERROR(H46/H$3,0) -> 8.0740502e-06 | AC46: =IFERROR(I46/I$3,0) -> 3.4707007e-06 | AD46: =IFERROR(J46/J$3,0) -> 2.6289282e-06 | AE46: =IFERROR(K46/K$3,0) -> 2.9944067e-06 | AG46: =IFERROR(H46-G46,0) -> 0.12125041 | AH46: =IFERROR(I46-H46,0) -> -0.12332162 | AI46: =IFERROR(J46-I46,0) -> -0.018881916 | AJ46: =IFERROR(K46-J46,0) -> 0.025329395 | AL46: =IFERROR((H46-G46)/G46,0) -> 1.0506968 | AM46: =IFERROR((I46-H46)/H46,0) -> -0.52111307 | AN46: =IFERROR((J46-I46)/I46,0) -> -0.16661182 | AO46: =IFERROR((K46-J46)/J46,0) -> 0.26818669
A47: Margen EBITDA % | G47: =IFERROR(G45/G3,0) -> 0.68911014 | H47: =IFERROR(H45/H3,0) -> 0.70085295 | I47: =IFERROR(I45/I3,0) -> 0.70039506 | J47: =IFERROR(J45/J3,0) -> 0.6967099 | K47: =IFERROR(K45/K3,0) -> 0.7007 | AA47: =IFERROR(G47/G$3,0) -> 2.8587851e-05 | AB47: =IFERROR(H47/H$3,0) -> 2.3911735e-05 | AC47: =IFERROR(I47/I$3,0) -> 2.1449639e-05 | AD47: =IFERROR(J47/J$3,0) -> 1.9392916e-05 | AE47: =IFERROR(K47/K$3,0) -> 1.75175e-05 | AG47: =IFERROR(H47-G47,0) -> 0.011742808 | AH47: =IFERROR(I47-H47,0) -> -0.00045788797 | AI47: =IFERROR(J47-I47,0) -> -0.0036851595 | AJ47: =IFERROR(K47-J47,0) -> 0.0039900963 | AL47: =IFERROR((H47-G47)/G47,0) -> 0.017040539 | AM47: =IFERROR((I47-H47)/H47,0) -> -0.00065332959 | AN47: =IFERROR((J47-I47)/I47,0) -> -0.0052615442 | AO47: =IFERROR((K47-J47)/J47,0) -> 0.0057270555
A48: EBIT | G48: =G14 -> 15807 | H48: =H14 -> 19681 | I48: =I14 -> 21927 | J48: =J14 -> 23996 | K48: =K14 -> 26808 | AA48: =IFERROR(G48/G$3,0) -> 0.65575607 | AB48: =IFERROR(H48/H$3,0) -> 0.67147731 | AC48: =IFERROR(I48/I$3,0) -> 0.67151563 | AD48: =IFERROR(J48/J$3,0) -> 0.66792852 | AE48: =IFERROR(K48/K$3,0) -> 0.6702 | AG48: =IFERROR(H48-G48,0) -> 3874 | AH48: =IFERROR(I48-H48,0) -> 2246 | AI48: =IFERROR(J48-I48,0) -> 2069 | AJ48: =IFERROR(K48-J48,0) -> 2812 | AL48: =IFERROR((H48-G48)/G48,0) -> 0.24508129 | AM48: =IFERROR((I48-H48)/H48,0) -> 0.11412022 | AN48: =IFERROR((J48-I48)/I48,0) -> 0.094358553 | AO48: =IFERROR((K48-J48)/J48,0) -> 0.1171862

Sheet Supuestos FCL
A1: SUPUESTOS PARA EL MODELO DE FLUJO DE CAJA LIBRE (FCL) - VISA INC.
A4: A. DATOS GENERALES
A5: Concepto | B5: Valor | C5: Fuente / Nota
A6: Cierre de año fiscal de VISA | B6: 30-sep | C6: 10-K de VISA Inc. (SEC EDGAR)
A7: Horizonte histórico analizado | B7: FY2021-FY2025 | C7: Taller - Análisis financiero VISA - LyL.xlsx (Balance, PyG)
A8: Horizonte de proyección del FCL | B8: FY2026-FY2030 (5 años) | C8: Supuesto propio, igual al horizonte usado en los ejercicios de clase
A10: B. DATOS BASE - AÑO FISCAL 2025
A11: Concepto | B11: Valor | C11: Fuente / Nota
A12: Ingresos totales 2024 (US$ MM) | B12: 35926 | C12: Taller VISA, hoja PyG - Ingresos totales
A13: Ingresos totales 2025 (US$ MM) | B13: 40000 | C13: Taller VISA, hoja PyG - Ingresos totales
A14: EBIT 2025 (US$ MM) | B14: 26808 | C14: Taller VISA, hoja PyG - EBIT
A15: Margen EBIT 2025 | B15: =$B$14/$B$13 -> 0.6702 | C15: Calculado = EBIT 2025 / Ingresos 2025
A16: D&A 2025 (US$ MM) | B16: 1220 | C16: Taller VISA, hoja PyG (EBITDA - EBIT = 28,028 - 26,808)
A17: % D&A / Ingresos 2025 | B17: =$B$16/$B$13 -> 0.0305 | C17: Calculado = D&A 2025 / Ingresos 2025
A18: Capex real 2025 (US$ MM) | B18: 1482 | C18: stockanalysis.com, Estado de flujo de efectivo de VISA (basado en 10-K); no se usa el neto de PP&E del Balance porque no discrimina retiros de activos
A19: % Capex / Ingresos 2025 | B19: =$B$18/$B$13 -> 0.03705 | C19: Calculado = Capex 2025 / Ingresos 2025
A20: Cuentas por cobrar 2025 (US$ MM) | B20: 7317 | C20: Taller VISA, hoja Balance
A21: Proveedores 2025 (US$ MM) | B21: 555 | C21: Taller VISA, hoja Balance
A22: KTNO 2025 (US$ MM) = CxC + Inventario(0) - Proveedores | B22: =$B$20-$B$21 -> 6762
A23: % KTNO / Ingresos 2025 | B23: =$B$22/$B$13 -> 0.16905 | C23: Calculado = KTNO 2025 / Ingresos 2025
A24: Tasa de impuesto de renta efectiva 2025 | B24: 0.170951 | C24: Taller VISA, hoja EVA (Empresa) = Impuesto de renta / EBT 2025
A25: Deuda financiera total 2025 (US$ MM) | B25: 26084 | C25: Taller VISA, hoja Balance / WACC Visa
A26: Efectivo y equivalentes 2025 (US$ MM) | B26: 17164 | C26: Taller VISA, hoja Balance
A27: Deuda neta 2025 (US$ MM) | B27: =$B$25-$B$26 -> 8920
A28: Acciones en circulación 2025 (millones) | B28: 1966 | C28: Taller VISA, hoja Ratios (Acciones en circulación)
A29: Precio de mercado 2025 (US$/acción) | B29: 223.6465 | C29: Taller VISA, hoja Ratios (Precio de mercado)
A31: C. SUPUESTOS DE PROYECCIÓN FY2026-FY2030
A32: Concepto | B32: Valor | C32: Fuente / Nota
A33: Crecimiento de ingresos FY2026 | B33: 0.11 | C33: Consenso de analistas: ingresos FY2026 proyectados en ~US$45,000-45,800 MM (Yahoo Finance / Stockanalysis.com forecast, sep-2026)
A34: Crecimiento de ingresos FY2027 | B34: 0.105 | C34: Consenso de analistas: ingresos FY2027 proyectados en ~US$49,700-50,600 MM (Yahoo Finance / Stockanalysis.com forecast, sep-2026)
A35: Crecimiento de ingresos FY2028 | B35: 0.095 | C35: Supuesto propio: desaceleración gradual hacia el crecimiento de largo plazo de una empresa madura de gran capitalización
A36: Crecimiento de ingresos FY2029 | B36: 0.09 | C36: Supuesto propio: continúa la convergencia gradual del crecimiento
A37: Crecimiento de ingresos FY2030 | B37: 0.085 | C37: Supuesto propio: continúa la convergencia gradual del crecimiento
A38: Margen EBIT proyectado (constante FY26-FY30) | B38: =$B$15 -> 0.6702 | C38: Supuesto propio: se mantiene el margen operativo 2025 dado el modelo de negocio de red de pagos, altamente escalable y con costos incrementales bajos
A39: % D&A / Ingresos proyectado (constante) | B39: =$B$17 -> 0.0305 | C39: Supuesto propio: la depreciación y amortización se mantiene proporcional a los ingresos
A40: % Capex / Ingresos proyectado (constante) | B40: =$B$19 -> 0.03705 | C40: Supuesto propio: la inversión en activos fijos se mantiene proporcional al crecimiento del negocio
A41: % KTNO / Ingresos proyectado (constante) | B41: =$B$23 -> 0.16905 | C41: Supuesto propio: la necesidad de capital de trabajo neto operativo se mantiene proporcional a los ingresos
A42: Tasa de impuesto de renta proyectada (constante) | B42: =$B$24 -> 0.170951 | C42: Supuesto propio: se mantiene la tasa efectiva de 2025
A43: WACC (método Empresa - beta de regresión) usado para descontar el FCL | B43: 0.064487 | C43: Taller VISA, hoja 'WACC Visa' (panel 'Empresa')
A44: WACC (método Sector - beta apalancada Damodaran), alterno para sensibilidad | B44: 0.074677 | C44: Taller VISA, hoja 'WACC Visa' (panel 'Sector')
A45: Tasa de crecimiento a perpetuidad (g) | B45: 0.03 | C45: Supuesto propio: cercana al crecimiento nominal de largo plazo de la economía global; debe ser menor al WACC para que el valor terminal converja

Sheet FCL Histórico
A1: SUPUESTOS PARA EL MODELO DE FLUJO DE CAJA LIBRE (FCL) - VISA INC.
A3: B. DATOS BASE - AÑO FISCAL 2025
A4: Ingresos totales 2024 (US$ MM) | B4: 35926
A5: Ingresos totales 2025 (US$ MM) | B5: 40000
A6: EBIT 2025 (US$ MM) | B6: 26808
A7: Margen EBIT 2025 | B7: =+B6/B5 -> 0.6702
A8: D&A 2025 (US$ MM) | B8: 1220
A9: % D&A / Ingresos 2025 | B9: =+B8/B5 -> 0.0305
A10: Capex real 2025 (US$ MM) | B10: 1482
A11: % Capex / Ingresos 2025 | B11: =+B10/B5 -> 0.03705
A12: Cuentas por cobrar 2025 (US$ MM) | B12: 7317
A13: Proveedores 2025 (US$ MM) | B13: 555
A14: KTNO 2025 (US$ MM) = CxC + Inventario(0) - Proveedores | B14: =+B12-B13 -> 6762
A15: % KTNO / Ingresos 2025 | B15: =+B14/B5 -> 0.16905
A16: Tasa de impuesto de renta efectiva 2025 | B16: 0.170951
A17: Deuda financiera total 2025 (US$ MM) | B17: 26084
A18: Efectivo y equivalentes 2025 (US$ MM) | B18: 17164
A19: Deuda neta 2025 (US$ MM) | B19: =+B17-B18 -> 8920
A20: Acciones en circulación 2025 (millones) | B20: 1966
A21: Precio de mercado 2025 (US$/acción) | B21: 223.6465
A23: FLUJO DE CAJA LIBRE HISTÓRICO - VISA INC. (FY2021-FY2025)
A25: CIFRAS DE ESTADOS FINANCIEROS
A26: Concepto | B26: 2021 | C26: 2022 | D26: 2023 | E26: 2024 | F26: 2025
A27: Ingresos totales | B27: 24105 | C27: 29310 | D27: 32653 | E27: 35926 | F27: 40000
A28: EBIT (Utilidad Operacional) | B28: 15807 | C28: 19681 | D28: 21927 | E28: 23996 | F28: 26808
A29: EBITDA | B29: 16611 | C29: 20542 | D29: 22870 | E29: 25030 | F29: 28028
A30: Tasa de impuesto de renta efectiva | B30: 0.23358 | C30: 0.175287 | D30: 0.178923 | E30: 0.174486 | F30: 0.170951
A31: Capex real (fuente stockanalysis.com, CFI) | B31: 705 | C31: 970 | D31: 1059 | E31: 1257 | F31: 1482
A32: Cuentas por cobrar | B32: 3726 | C32: 3952 | D32: 4474 | E32: 7015 | F32: 7317
A33: Inventario | B33: 0 | C33: 0 | D33: 0 | E33: 0 | F33: 0
A34: Proveedores | B34: 266 | C34: 340 | D34: 375 | E34: 479 | F34: 555
A36: CÁLCULO DEL KTNO
A37: Concepto | B37: 2021 | C37: 2022 | D37: 2023 | E37: 2024 | F37: 2025
A38: Cuentas por cobrar | B38: =+B32 -> 3726 | C38: =+C32 -> 3952 | D38: =+D32 -> 4474 | E38: =+E32 -> 7015 | F38: =+F32 -> 7317
A39: (+) Inventario | B39: =+B33 -> 0 | C39: =+C33 -> 0 | D39: =+D33 -> 0 | E39: =+E33 -> 0 | F39: =+F33 -> 0
A40: (-) Proveedores | B40: =-B34 -> -266 | C40: =-C34 -> -340 | D40: =-D34 -> -375 | E40: =-E34 -> -479 | F40: =-F34 -> -555
A41: KTNO = Cuentas por cobrar + Inventario - Proveedores | B41: =SUM(B38:B40) -> 3460 | C41: =SUM(C38:C40) -> 3612 | D41: =SUM(D38:D40) -> 4099 | E41: =SUM(E38:E40) -> 6536 | F41: =SUM(F38:F40) -> 6762
A42: Variación del KTNO (inversión incremental) | C42: =C41-B41 -> 152 | D42: =D41-C41 -> 487 | E42: =E41-D41 -> 2437 | F42: =F41-E41 -> 226
A44: ESTADO DE RESULTADOS Y FLUJO DE CAJA LIBRE HISTÓRICO (millones US$)
A45: Concepto | B45: 2021 | C45: 2022 | D45: 2023 | E45: 2024 | F45: 2025
A46: EBIT (Utilidad Operacional) | B46: =+B28 -> 15807 | C46: =+C28 -> 19681 | D46: =+D28 -> 21927 | E46: =+E28 -> 23996 | F46: =+F28 -> 26808
A47: (-) Impuesto de renta (Tasa efectiva x EBIT) | B47: =-B46*B30 -> -3692.1991 | C47: =-C46*C30 -> -3449.8234 | D47: =-D46*D30 -> -3923.2446 | E47: =-E46*E30 -> -4186.9661 | F47: =-F46*F30 -> -4582.8544
A48: → UODI (Utilidad Operativa Después de Impuestos) | B48: =B46+B47 -> 12114.801 | C48: =C46+C47 -> 16231.177 | D48: =D46+D47 -> 18003.755 | E48: =E46+E47 -> 19809.034 | F48: =F46+F47 -> 22225.146
A49: (+) Depreciación y amortización (D&A = EBITDA - EBIT) | B49: =B29-B28 -> 804 | C49: =C29-C28 -> 861 | D49: =D29-D28 -> 943 | E49: =E29-E28 -> 1034 | F49: =F29-F28 -> 1220
A50: Flujo de Caja Bruto | B50: =B48+B49 -> 12918.801 | C50: =C48+C49 -> 17092.177 | D50: =D48+D49 -> 18946.755 | E50: =E48+E49 -> 20843.034 | F50: =F48+F49 -> 23445.146
A51: (-) Inversión incremental del KTNO | C51: =-C42 -> -152 | D51: =-D42 -> -487 | E51: =-E42 -> -2437 | F51: =-F42 -> -226
A52: (-) Capex (inversión en activos fijos) | B52: =-B31 -> -705 | C52: =-C31 -> -970 | D52: =-D31 -> -1059 | E52: =-E31 -> -1257 | F52: =-F31 -> -1482
A53: → FLUJO DE CAJA LIBRE (FCL) | C53: =C50+C51+C52 -> 15970.177 | D53: =D50+D51+D52 -> 17400.755 | E53: =E50+E51+E52 -> 17149.034 | F53: =F50+F51+F52 -> 21737.146
A55: CRECIMIENTO DEL FCL Y DE LOS INGRESOS
A56: Concepto | B56: 2022/2021 | C56: 2023/2022 | D56: 2024/2023 | E56: 2025/2024
A57: Crecimiento de ingresos | B57: =C27/B27-1 -> 0.2159303 | C57: =D27/C27-1 -> 0.11405664 | D57: =E27/D27-1 -> 0.10023581 | E57: =F27/E27-1 -> 0.11339977
A58: Crecimiento del FCL | C58: =D53/C53-1 -> 0.089578147 | D58: =E53/D53-1 -> -0.014466121 | E58: =F53/E53-1 -> 0.26754345

Sheet FCL Proyectado
A1: FLUJO DE CAJA LIBRE PROYECTADO Y VALORACIÓN - VISA INC. (FY2026-FY2030)
A3: SUPUESTOS DE PROYECCIÓN FY2026-FY2030
A4: Concepto | B4: Valor
A5: Crecimiento de ingresos FY2026 | B5: 0.11
A6: Crecimiento de ingresos FY2027 | B6: 0.105
A7: Crecimiento de ingresos FY2028 | B7: 0.095
A8: Crecimiento de ingresos FY2029 | B8: 0.09
A9: Crecimiento de ingresos FY2030 | B9: 0.085
A10: Margen EBIT proyectado (constante FY26-FY30) | B10: =+'FCL Histórico'!B7 -> 0.6702
A11: % D&A / Ingresos proyectado (constante) | B11: =+'FCL Histórico'!B9 -> 0.0305
A12: % Capex / Ingresos proyectado (constante) | B12: =+'FCL Histórico'!B11 -> 0.03705
A13: % KTNO / Ingresos proyectado (constante) | B13: =+'FCL Histórico'!B15 -> 0.16905
A14: Tasa de impuesto de renta proyectada (constante) | B14: =+'FCL Histórico'!B16 -> 0.170951
A15: WACC (método Empresa - beta de regresión) usado para descontar el FCL | B15: 0.064487
A16: WACC (método Sector - beta apalancada Damodaran), alterno para sensibilidad | B16: 0.074677
A17: Tasa de crecimiento a perpetuidad (g) | B17: 0.03
A20: PROYECCIÓN DE INGRESOS Y UAII (UODI)
A21: Concepto | B21: 2025 (real) | C21: FY2026 | D21: FY2027 | E21: FY2028 | F21: FY2029 | G21: FY2030
A22: Ingresos totales | B22: =+'FCL Histórico'!F27 -> 40000 | C22: =B22*(1+B5) -> 44400 | D22: =C22*(1+B6) -> 49062 | E22: =D22*(1+B7) -> 53722.89 | F22: =E22*(1+B8) -> 58557.95 | G22: =F22*(1+B9) -> 63535.376
A23: Crecimiento de ingresos | C23: =+B5 -> 0.11 | D23: =+B6 -> 0.105 | E23: =+B7 -> 0.095 | F23: =+B8 -> 0.09 | G23: =+B9 -> 0.085
A24: EBIT (Ingresos x Margen EBIT) | B24: =B22*$B$10 -> 26808 | C24: =C22*$B$10 -> 29756.88 | D24: =D22*$B$10 -> 32881.352 | E24: =E22*$B$10 -> 36005.081 | F24: =F22*$B$10 -> 39245.538 | G24: =G22*$B$10 -> 42581.409
A25: (-) Impuesto de renta (Tasa efectiva x EBIT) | B25: =-B24*$B$14 -> -4582.8544 | C25: =-C24*$B$14 -> -5086.9684 | D25: =-D24*$B$14 -> -5621.1001 | E25: =-E24*$B$14 -> -6155.1046 | F25: =-F24*$B$14 -> -6709.064 | G25: =-G24*$B$14 -> -7279.3344
A26: UODI (Utilidad Operativa Después de Impuestos) | B26: =B24+B25 -> 22225.146 | C26: =C24+C25 -> 24669.912 | D26: =D24+D25 -> 27260.252 | E26: =E24+E25 -> 29849.976 | F26: =F24+F25 -> 32536.474 | G26: =G24+G25 -> 35302.074
A29: FLUJO DE CAJA LIBRE PROYECTADO
A30: Concepto | B30: 2025 (real) | C30: FY2026 | D30: FY2027 | E30: FY2028 | F30: FY2029 | G30: FY2030
A31: Utilidad Operativa Después de Impuestos (UODI) | B31: =+B26 -> 22225.146 | C31: =+C26 -> 24669.912 | D31: =+D26 -> 27260.252 | E31: =+E26 -> 29849.976 | F31: =+F26 -> 32536.474 | G31: =+G26 -> 35302.074
A32: (+) Depreciación y amortización (D&A) | B32: =B22*$B$11 -> 1220 | C32: =C22*$B$11 -> 1354.2 | D32: =D22*$B$11 -> 1496.391 | E32: =E22*$B$11 -> 1638.5481 | F32: =F22*$B$11 -> 1786.0175 | G32: =G22*$B$11 -> 1937.829
A33: Flujo de Caja Bruto | B33: =B26+B32 -> 23445.146 | C33: =C26+C32 -> 26024.112 | D33: =D26+D32 -> 28756.643 | E33: =E26+E32 -> 31488.524 | F33: =F26+F32 -> 34322.492 | G33: =G26+G32 -> 37239.903
A34: KTNO (Ingresos x % KTNO supuesto) | B34: =+'FCL Histórico'!B14 -> 6762 | C34: =C22*$B$13 -> 7505.82 | D34: =D22*$B$13 -> 8293.9311 | E34: =E22*$B$13 -> 9081.8546 | F34: =F22*$B$13 -> 9899.2215 | G34: =G22*$B$13 -> 10740.655
A35: (-) Variación del KTNO (inversión incremental) | C35: =-(C34-B34) -> -743.82 | D35: =-(D34-C34) -> -788.1111 | E35: =-(E34-D34) -> -787.92345 | F35: =-(F34-E34) -> -817.36691 | G35: =-(G34-F34) -> -841.43382
A36: (-) Capex (Ingresos x % Capex supuesto) | C36: =-C22*$B$12 -> -1645.02 | D36: =-D22*$B$12 -> -1817.7471 | E36: =-E22*$B$12 -> -1990.4331 | F36: =-F22*$B$12 -> -2169.5721 | G36: =-G22*$B$12 -> -2353.9857
A37: FLUJO DE CAJA LIBRE (FCL) PROYECTADO | C37: =C33+C35+C36 -> 23635.272 | D37: =D33+D35+D36 -> 26150.785 | E37: =E33+E35+E36 -> 28710.168 | F37: =F33+F35+F36 -> 31335.553 | G37: =G33+G35+G36 -> 34044.484
A39: VALORACIÓN POR FLUJO DE CAJA DESCONTADO (DCF) - MÉTODO EMPRESA
A40: Concepto | C40: FY2026 | D40: FY2027 | E40: FY2028 | F40: FY2029 | G40: FY2030
A41: Factor de descuento = 1/(1+WACC)^n | C41: =1/(1+'Supuestos FCL'!$B$43)^1 -> 0.93941965 | D41: =1/(1+'Supuestos FCL'!$B$43)^2 -> 0.88250927 | E41: =1/(1+'Supuestos FCL'!$B$43)^3 -> 0.82904655 | F41: =1/(1+'Supuestos FCL'!$B$43)^4 -> 0.77882261 | G41: =1/(1+'Supuestos FCL'!$B$43)^5 -> 0.73164126
A42: Valor presente del FCL | C42: =C37*C41 -> 22203.438 | D42: =D37*D41 -> 23078.31 | E42: =E37*E41 -> 23802.066 | F42: =F37*F41 -> 24404.837 | G42: =G37*G41 -> 24908.349
A44: Valor terminal (Gordon) = FCL FY2030 x (1+g) / (WACC - g) | B44: =G37*(1+'Supuestos FCL'!$B$45)/('Supuestos FCL'!$B$43-'Supuestos FCL'!$B$45) -> 1016783.7
A45: Valor presente del valor terminal | B45: =B44*G41 -> 743920.89
A47: → VALOR DE LA EMPRESA (EV) = Σ VP(FCL) + VP(Valor Terminal) | B47: =SUM(C42:G42)+B45 -> 862317.89
A48: (-) Deuda neta 2025 (Deuda financiera - Efectivo) | B48: =-'Supuestos FCL'!$B$27 -> -8920
A49: → VALOR DEL PATRIMONIO (Equity Value) | B49: =B47+B48 -> 853397.89
A50: Acciones en circulación 2025 (millones) | B50: ='Supuestos FCL'!$B$28 -> 1966
A51: → VALOR INTRÍNSECO POR ACCIÓN (DCF) | B51: =B49/B50 -> 434.07827
A52: Precio de mercado 2025 (referencia) | B52: ='Supuestos FCL'!$B$29 -> 223.6465
A53: Upside / (downside) del valor intrínseco vs. precio de mercado | B53: =B51/B52-1 -> 0.94091244
A57: ANÁLISIS DE SENSIBILIDAD - VALOR INTRÍNSECO POR ACCIÓN (US$/acción)
A58: WACC \ g | B58: 0.025 | C58: 0.03 | D58: 0.035
A59: WACC Empresa | B59: =(SUMPRODUCT($C$37:$G$37,1/(1+'Supuestos FCL'!$B$43)^{1,2,3,4,5})+$G$37*(1+0.025)/('Supuestos FCL'!$B$43-0.025)/(1+'Supuestos FCL'!$B$43)^5-'Supuestos FCL'!$B$27)/'Supuestos FCL'!$B$28 -> 384.56037 | C59: =(SUMPRODUCT($C$37:$G$37,1/(1+'Supuestos FCL'!$B$43)^{1,2,3,4,5})+$G$37*(1+0.03)/('Supuestos FCL'!$B$43-0.03)/(1+'Supuestos FCL'!$B$43)^5-'Supuestos FCL'!$B$27)/'Supuestos FCL'!$B$28 -> 434.07827 | D59: =(SUMPRODUCT($C$37:$G$37,1/(1+'Supuestos FCL'!$B$43)^{1,2,3,4,5})+$G$37*(1+0.035)/('Supuestos FCL'!$B$43-0.035)/(1+'Supuestos FCL'!$B$43)^5-'Supuestos FCL'!$B$27)/'Supuestos FCL'!$B$28 -> 500.38931
A60: WACC Sector | B60: =(SUMPRODUCT($C$37:$G$37,1/(1+'Supuestos FCL'!$B$44)^{1,2,3,4,5})+$G$37*(1+0.025)/('Supuestos FCL'!$B$44-0.025)/(1+'Supuestos FCL'!$B$44)^5-'Supuestos FCL'!$B$27)/'Supuestos FCL'!$B$28 -> 303.21575 | C60: =(SUMPRODUCT($C$37:$G$37,1/(1+'Supuestos FCL'!$B$44)^{1,2,3,4,5})+$G$37*(1+0.03)/('Supuestos FCL'!$B$44-0.03)/(1+'Supuestos FCL'!$B$44)^5-'Supuestos FCL'!$B$27)/'Supuestos FCL'!$B$28 -> 332.4628 | D60: =(SUMPRODUCT($C$37:$G$37,1/(1+'Supuestos FCL'!$B$44)^{1,2,3,4,5})+$G$37*(1+0.035)/('Supuestos FCL'!$B$44-0.035)/(1+'Supuestos FCL'!$B$44)^5-'Supuestos FCL'!$B$27)/'Supuestos FCL'!$B$28 -> 369.08113
A61: Precio de mercado 2025 (referencia) | B61: ='Supuestos FCL'!$B$29 -> 223.6465

Sheet Supuestos Apalancamiento
A1: SUPUESTOS PARA EL ANÁLISIS DE APALANCAMIENTO - VISA INC.
A3: A. DATOS BASE - AÑO FISCAL 2025 (PyG de VISA)
A4: Concepto | B4: Valor | C4: Fuente / Nota
A5: Ingresos totales 2024 (US$ MM) | B5: 35926 | C5: Taller VISA, hoja PyG
A6: Ingresos totales 2025 (US$ MM) | B6: 40000 | C6: Taller VISA, hoja PyG
A7: Coste de los ingresos 2025 (US$ MM) | B7: 894 | C7: Taller VISA, hoja PyG - Coste de los ingresos
A8: Total de otros gastos operativos 2025 (US$ MM) [SG&A + D&A] | B8: 12298 | C8: Taller VISA, hoja PyG - Total de otros gastos operativos
A9: EBIT 2025 verificado = Ventas - Costo Variable - Costo Fijo | B9: =$B$6-$B$7-$B$8 -> 26808 | C9: Debe coincidir con el EBIT reportado en el PyG (US$26,808 MM)
A10: Gastos financieros (intereses) 2025 (US$ MM) | B10: 589 | C10: Taller VISA, hoja PyG - Total de gastos de intereses
A11: Tasa de impuesto de renta efectiva 2025 | B11: 0.170951 | C11: Taller VISA, hoja EVA (Empresa)
A12: Acciones en circulación 2025 (millones) | B12: 1966 | C12: Taller VISA, hoja Ratios
A13: Precio de mercado 2025 (US$/acción) | B13: 223.6465 | C13: Taller VISA, hoja Ratios
A15: B. CLASIFICACIÓN DE COSTOS EN VARIABLES Y FIJOS (supuesto propio)
A16: • Costo variable = 'Coste de los ingresos' (costos de procesamiento y de la red que se incurren por cada transacción/volumen procesado). • Costo fijo = 'Total de otros gastos operativos' (SG&A, D&A y otros gastos operativos), que no varían directamente con el volumen transaccional en el corto plazo. Esta clasificación es consistente con el modelo de negocio de VISA, ampliamente reconocido como un negocio de altísimo apalancamiento operativo: su costo de los ingresos históricamente representa entre 2% y 3% de las ventas, mientras la gran mayoría de la estructura de costos es de naturaleza fija/semifija.
A18: C. ESCENARIO DE FINANCIAMIENTO MARGINAL (para el punto de indiferencia UPA: Deuda vs. Patrimonio)
A19: Concepto | B19: Valor | C19: Fuente / Nota
A20: Necesidad de financiamiento adicional (US$ MM) | B20: 5000 | C20: Supuesto propio: monto hipotético para un proyecto de expansión / adquisición o programa de recompra de acciones adicional
A21: Tasa de interés de la deuda nueva (Kd, antes de impuestos) | B21: 0.05 | C21: Igual al Kd usado en el Taller VISA, hoja 'WACC Visa' (costo de la deuda de VISA)
A22: Precio de emisión de las acciones nuevas (Opción A) | B22: =$B$13 -> 223.6465 | C22: Supuesto propio: se emiten al precio de mercado 2025, sin descuento por colocación

Sheet Apalancamiento GAO-GAF
A1: APALANCAMIENTO OPERATIVO Y FINANCIERO - VISA INC. (FY2025)
A3: A. DATOS BASE - AÑO FISCAL 2025 (PyG de VISA)
A4: Concepto | B4: Valor
A5: Ingresos totales 2024 (US$ MM) | B5: =+PyG!J3 -> 35926
A6: Ingresos totales 2025 (US$ MM) | B6: =+PyG!K3 -> 40000
A7: Coste de los ingresos 2025 (US$ MM) | B7: =+PyG!K5 -> 894
A8: Total de otros gastos operativos 2025 (US$ MM) [SG&A + D&A] | B8: =+PyG!K9 -> 12298
A9: EBIT 2025 verificado = Ventas - Costo Variable - Costo Fijo | B9: =$B$6-$B$7-$B$8 -> 26808
A10: Gastos financieros (intereses) 2025 (US$ MM) | B10: =-PyG!K19 -> 589
A11: Tasa de impuesto de renta efectiva 2025 | B11: 0.170951
A12: Acciones en circulación 2025 (millones) | B12: 1966
A13: Precio de mercado 2025 (US$/acción) | B13: 223.6465
A15: DATOS DEL ENUNCIADO
A16: Concepto | B16: Valor
A17: Ventas (Ingresos totales) 2025 | B17: =+B6 -> 40000
A18: Costos Variables 2025 (Coste de los ingresos) | B18: =+B7 -> 894
A19: Costos Fijos 2025 (SG&A + D&A + otros) | B19: =+B8 -> 12298
A20: Gastos financieros (intereses) 2025 | B20: =+B10 -> 589
A21: Tasa de impuesto de renta efectiva 2025 | B21: =+B11 -> 0.170951
A23: Cálculo del punto de equilibrio
A24: Margen de Contribución = Ventas - Costos Variables | B24: =B17-B18 -> 39106
A25: % Margen de Contribución sobre Ventas | B25: =B24/B17 -> 0.97765
A26: EBIT (Utilidad Operativa) = Margen de Contribución - Costos Fijos | B26: =B24-B19 -> 26808
A27: → PUNTO DE EQUILIBRIO (en ingresos) = Costos Fijos / % Margen de Contribución | B27: =B19/B25 -> 12579.144
B28: =B27-B27*(B18/B17)-B19 -> 0
A30: b) GRADO DE APALANCAMIENTO OPERATIVO (GAO) 2025 -> GAO = Margen de Contribución / EBIT
A31: → GAO 2025 | B31: =B24/B26 -> 1.4587437
A32: Interpretación: por cada 1% de variación en las ventas, el EBIT varía en (GAO x 1%)
A34: Comprobación del GAO (duplicando las ventas, igual que en el ejercicio de clase)
A35: Concepto | B35: Base (2025) | C35: Ventas x2
A36: Ventas | B36: =B17 -> 40000 | C36: =B17*2 -> 80000
A37: Costos Variables (% Ventas constante) | B37: =B18 -> 894 | C37: =C36*(B18/B17) -> 1788
A38: Costos Fijos | B38: =B19 -> 12298 | C38: =B19 -> 12298
A39: EBIT | B39: =B36-B37-B38 -> 26808 | C39: =C36-C37-C38 -> 65914
A40: % Variación en Ventas | C40: =C36/B36-1 -> 1
A41: % Variación en el EBIT | C41: =C39/B39-1 -> 1.4587437
A42: GAO verificado = %ΔEBIT / %ΔVentas | C42: =C41/C40 -> 1.4587437
A44: c) GRADO DE APALANCAMIENTO FINANCIERO (GAF) 2025 -> GAF = EBIT / (EBIT - Intereses)
A45: EBIT 2025 | B45: =B26 -> 26808
A46: (-) Intereses 2025 | B46: =-B20 -> -589
A47: → UAI (Utilidad Antes de Impuestos) | B47: =B26-B20 -> 26219
A48: → GAF 2025 | B48: =B26/B47 -> 1.0224646
A49: Interpretación: por cada 1% de variación en el EBIT, la utilidad antes de impuestos varía en (GAF x 1%)
A51: d) GRADO DE APALANCAMIENTO TOTAL (GCT) = GAO x GAF
A52: → GCT 2025 | B52: =B31*B48 -> 1.4915138
A55: e) VERIFICACIÓN CON EL CAMBIO REAL DE VENTAS 2024→2025 (Análisis Horizontal)
A56: Concepto | B56: 2024 | C56: 2025
A57: Ventas | B57: ='Supuestos Apalancamiento'!$B$5 -> 35926 | C57: =B17 -> 40000
A58: EBIT real reportado (Taller VISA, hoja PyG) | B58: 23996 | C58: =B26 -> 26808
A59: % Variación real de Ventas 2024→2025 | C59: =C57/B57-1 -> 0.11339977
A60: % Variación real del EBIT 2024→2025 | C60: =C58/B58-1 -> 0.1171862
A61: GAO implícito real = %ΔEBIT real / %ΔVentas real | C61: =C60/C59 -> 1.0333901
A62: Nota: el GAO 'implícito real' (calculado con el cambio efectivo de ventas y EBIT entre 2024 y 2025) puede diferir del GAO teórico (b), porque en la realidad los costos fijos y el mix de ingresos también cambiaron de un año a otro; el GAO teórico asume una estructura de costos constante, como en el ejercicio de clase.

Sheet UPA Deuda vs Patrimonio
A1: UPA: PUNTO DE INDIFERENCIA ENTRE DEUDA Y EMISIÓN DE ACCIONES - VISA INC.
A2: Metodología igual a los ejercicios vistos en clase, extendida para incorporar los intereses de la deuda ya existente de VISA (589 US$ MM en 2025), y no solo los de la deuda nueva, ya que a diferencia de los ejercicios de clase VISA es una empresa en marcha con deuda previa.
A4: DATOS DEL ESCENARIO (enlazados desde Supuestos Apalancamiento)
A5: Concepto | B5: Valor
A6: Necesidad de financiamiento adicional (US$ MM) | B6: ='Supuestos Apalancamiento'!$B$20 -> 5000
A7: Tasa de interés de la deuda nueva (Kd pretax) | B7: ='Supuestos Apalancamiento'!$B$21 -> 0.05
A8: Precio de emisión de acciones nuevas (US$/acción) | B8: ='Supuestos Apalancamiento'!$B$22 -> 223.6465
A9: Acciones en circulación 2025 (millones) [Opción B - Deuda, N_B] | B9: ='Supuestos Apalancamiento'!$B$12 -> 1966
A10: Intereses de la deuda YA existente 2025 (US$ MM) | B10: ='Supuestos Apalancamiento'!$B$10 -> 589
A11: Tasa de impuesto de renta efectiva | B11: ='Supuestos Apalancamiento'!$B$11 -> 0.170951
A12: Intereses de la deuda NUEVA (Opción B) = Monto x Kd | B12: =B6*B7 -> 250
A13: Acciones nuevas emitidas (Opción A) = Monto / Precio de emisión (millones) | B13: =B6/B8 -> 22.35671
A14: → Acciones totales Opción A (Capital Propio, N_A) = N_B + Acciones nuevas | B14: =B9+B13 -> 1988.3567
A16: PUNTO DE INDIFERENCIA (EBIT*): UPA Opción A = UPA Opción B
A18: → EBIT* (punto de indiferencia, US$ MM) | B18: =B10+(B14*B12)/(B14-B9) -> 22823.451
A19: Comprobación - UPA Opción A en EBIT* | B19: =(B18-B10)*(1-B11)/B14 -> 9.2706954
A20: Comprobación - UPA Opción B en EBIT* | B20: =(B18-B10-B12)*(1-B11)/B9 -> 9.2706954
A21: Diferencia (debe ser ≈ 0) | B21: =B19-B20 -> 0
A23: TABLA UPA POR NIVEL DE EBIT: CAPITAL PROPIO (OPCIÓN A) VS. DEUDA (OPCIÓN B)
A24: EBIT (US$ MM) | B24: UAI Opción A | C24: Utilidad Neta A | D24: UPA Opción A (US$) | F24: UAI Opción B | G24: Utilidad Neta B | H24: UPA Opción B (US$)
A25: 10000 | B25: =A25-$B$10 -> 9411 | C25: =B25*(1-$B$11) -> 7802.1801 | D25: =C25/$B$14 -> 3.9239338 | F25: =A25-$B$10-$B$12 -> 9161 | G25: =F25*(1-$B$11) -> 7594.9179 | H25: =G25/$B$9 -> 3.8631322
A26: 15000 | B26: =A26-$B$10 -> 14411 | C26: =B26*(1-$B$11) -> 11947.425 | D26: =C26/$B$14 -> 6.008693 | F26: =A26-$B$10-$B$12 -> 14161 | G26: =F26*(1-$B$11) -> 11740.163 | H26: =G26/$B$9 -> 5.9715986
A27: 20000 | B27: =A27-$B$10 -> 19411 | C27: =B27*(1-$B$11) -> 16092.67 | D27: =C27/$B$14 -> 8.0934523 | F27: =A27-$B$10-$B$12 -> 19161 | G27: =F27*(1-$B$11) -> 15885.408 | H27: =G27/$B$9 -> 8.0800651
A28: 25000 | B28: =A28-$B$10 -> 24411 | C28: =B28*(1-$B$11) -> 20237.915 | D28: =C28/$B$14 -> 10.178212 | F28: =A28-$B$10-$B$12 -> 24161 | G28: =F28*(1-$B$11) -> 20030.653 | H28: =G28/$B$9 -> 10.188531
A29: 26808 | B29: =A29-$B$10 -> 26219 | C29: =B29*(1-$B$11) -> 21736.836 | D29: =C29/$B$14 -> 10.93206 | F29: =A29-$B$10-$B$12 -> 25969 | G29: =F29*(1-$B$11) -> 21529.573 | H29: =G29/$B$9 -> 10.950953
A30: 30000 | B30: =A30-$B$10 -> 29411 | C30: =B30*(1-$B$11) -> 24383.16 | D30: =C30/$B$14 -> 12.262971 | F30: =A30-$B$10-$B$12 -> 29161 | G30: =F30*(1-$B$11) -> 24175.898 | H30: =G30/$B$9 -> 12.296998
A31: 35000 | B31: =A31-$B$10 -> 34411 | C31: =B31*(1-$B$11) -> 28528.405 | D31: =C31/$B$14 -> 14.34773 | F31: =A31-$B$10-$B$12 -> 34161 | G31: =F31*(1-$B$11) -> 28321.143 | H31: =G31/$B$9 -> 14.405464
A32: 40000 | B32: =A32-$B$10 -> 39411 | C32: =B32*(1-$B$11) -> 32673.65 | D32: =C32/$B$14 -> 16.432489 | F32: =A32-$B$10-$B$12 -> 39161 | G32: =F32*(1-$B$11) -> 32466.388 | H32: =G32/$B$9 -> 16.513931
A33: 45000 | B33: =A33-$B$10 -> 44411 | C33: =B33*(1-$B$11) -> 36818.895 | D33: =C33/$B$14 -> 18.517248 | F33: =A33-$B$10-$B$12 -> 44161 | G33: =F33*(1-$B$11) -> 36611.633 | H33: =G33/$B$9 -> 18.622397
A35: La fila resaltada corresponde al EBIT real de VISA en FY2025 (US$26,808 MM).
A37: CONCLUSIÓN
A38: EBIT real 2025 vs. EBIT* de indiferencia: | B38: =IF('Apalancamiento GAO-GAF'!B26>B18,"EBIT real > EBIT* -> conviene financiar con DEUDA","EBIT real < EBIT* -> conviene financiar con ACCIONES") -> EBIT real > EBIT* -> conviene financiar con DEUDA
A39: Dado que el EBIT real de VISA en 2025 (US$26,808 MM) supera ampliamente el EBIT* de indiferencia calculado, financiar la necesidad adicional de US$5,000 MM con deuda nueva produce una UPA marginalmente mayor que emitir acciones nuevas al precio de mercado. Sin embargo, la diferencia es pequeña (ver tabla), lo cual es consistente con que VISA es una empresa de bajísimo apalancamiento financiero relativo a su generación de utilidad operativa (GAF≈1.02x, ver hoja 'Apalancamiento GAO-GAF'): a este nivel de rentabilidad, la decisión de financiamiento afecta poco la UPA, y otros factores (dilución, flexibilidad financiera, mantenimiento de la calificación crediticia) pesan tanto como el efecto aritmético sobre la UPA.
